Workbook

Sheet Read me
A1: Schema review workbook, genre: privacy (plan task 3.4: merge, split and prune clusters to 40-60 types)
A3: Yellow columns are yours. Grey columns are computed (Clusters, Claims, Noise sample) or proposed by Claude.
A4: Clusters sheet, 'Your action' (dropdown): accept = take the proposed action and type as they are;
A5: keep = the cluster is one type (give it in 'Your type'); merge = it joins the type in 'Your type' with
A6: other clusters; split = it holds several types (list them in 'Your type', comma-separated);
A7: prune = not a genre type (say why in 'Notes'). A row left blank blocks the schema.
A8: Types sheet: the proposed types with every field the frozen schema needs. Edit any cell, delete rows,
A9: add rows. Type ids must match what the Clusters sheet points to. Examples are claim texts.
A10: Severity weight: 1.0 by default; 1.5 for privacy types that GDPR Art. 13/14 or CCPA require.
A11: Section hint: where peers usually state it (used by the ghost-paragraph view).
A12: Label source (privacy): OPP-115 values that count as a positive, one per line, written
A13: 'Category :: Attribute = Value' or just 'Category' (lines are alternatives; '&' joins attribute values that
... A22: Provenance: cluster_run=cluster_v1_s0, name_run=name_72b_privacy_s0, naming=openai:openrouter.ai:qwen/qwen-2.5-72b-instruct@deepinfra/fp8, proposals=final_privacy.yaml

Sheet Summary
A1: Check | B1: Value
A2: Clusters | B2: =COUNTA(Clusters!A2:A75)
A3: Clusters still undecided | B3: =SUMPRODUCT((Clusters!A2:A75<>"")*(Clusters!T2:T75=""))
A4: Clusters pruned (your decisions) | B4: =COUNTIF(Clusters!T2:T75,"prune")
A5: Claims in pruned clusters | B5: =SUMIF(Clusters!T2:T75,"prune",Clusters!B2:B75)
A6: Types on the Types sheet | B6: =COUNTA(Types!A2:A500)
A7: Types within 40-60? | B7: =IF(AND(B6>=40,B6<=60),"yes","no")
A8: Types missing a required field | B8: =SUMPRODUCT((Types!A2:A500<>"")*(((Types!C2:C500="")+(Types!D2:D500="")+(Types!E2:E500="")+(Types!F2:F500="")+(Types!H2:H500="")+(Types!I2:I500=""))>0))
A9: Seeds still undecided | B9: =COUNTBLANK(Seeds!E2:E11)
A10: Kept-or-merged clusters with no type given | B10: =SUMPRODUCT((Clusters!T2:T75<>"")*(Clusters!T2:T75<>"accept")*(Clusters!T2:T75<>"prune")*(Clusters!U2:U75=""))

Sheet Clusters
A1: Cluster | B1: Size | C1: Documents | D1: Document share | E1: Cohesion | F1: Position (0 first, 1 last) | G1: Top headings | H1: Teacher name | I1: Teacher definition | J1: Flags | K1: Split note | L1: Representative 1 | M1: Representative 2 | N1: Representative 3 | O1: Top extraction labels | P1: Nearest clusters (cosine) | Q1: Proposed action | R1: Proposed type | S1: Reason | T1: Your action | U1: Your type | V1: Notes | W1: Effective type
A2: c000 | B2: 956 | C2: 355 | D2: 0.71 | E2: 0.6586 | F2: 0.437 | G2: cookies (236); (no heading) (130); use of cookies (65) | H2: cookie_usage_purposes | I2: States that the company uses cookies for various purposes, including to identify and track users, store preferences, and enhance the user experience. | L2: The company uses cookies to identify which pages on their website have been accessed. | M2: The company uses cookies for various purposes, including to access user information and track preferences. | N2: The company uses cookies to identify and track visitors and their preferences. | O2: cookie_usage (146), disclosing_practice (91), cookie_use (71), data_collection (36), data_use (30) | P2: c050 0.69, c053 0.61, c042 0.58 | Q2: merge | R2: uses_cookies | T2: accept | V2: reviewed on the page; see decisions/page_answers_2026-10-15.json and resolutions_2026-10-15.yaml | W2: =IF(T2="accept",R2,U2)
A3: c001 | B3: 835 | C3: 329 | D3: 0.658 | E3: 0.5602 | F3: 0.326 | G3: (no heading) (142); log files (22); privacy policy (14) | H3: collects_website_usage_data | I3: States that the company collects various types of data about user interactions with the website, including visits, page views, and technical information, but not specific personal data. | L3: The company collects information about the number of users visiting the website and the number of pages viewed. | M3: The company collects information about the visitor's use of the platform such as URLs visited, time spent, and actions taken. | N3: The company collects automated information about how users use and navigate the website. | O3: data_collection (167), data_use (70), specific_data_type (28), data_collection_purpose (23), data_usage (16) | P3: c060 0.73, c052 0.63, c002 0.55 | Q3: merge | R3: collects_usage_data_automatically | T3: accept | V3: reviewed on the page; see decisions/page_answers_2026-10-15.json and resolutions_2026-10-15.yaml | W3: =IF(T3="accept",R3,U3)
A4: c002 | B4: 651 | C4: 333 | D4: 0.666 | E4: 0.687 | F4: 0.178 | G4: (no heading) (107); what information do we collect (31); privacy policy (17) | H4: data_collection_methods | I4: States that the company collects personal information from users through various activities on the website, such as registration, placing orders, or providing information. | L4: The company collects personal information when users register or place an order on the site. | M4: The company collects various types of personal information from users, including contact details and demographic information. | N4: The company collects information when users place orders or enter information on the site. | O4: data_collection (318), data_collection_method (13), specific_data_collection (11), data_collection_purpose (9), data_collection_types (8) | P4: c001 0.55, c021 0.53, c060 0.46 | Q4: keep | R4: data_collection_methods | T4: accept | V4: reviewed on the page; see decisions/page_answers_2026-10-15.json and resolutions_2026-10-15.yaml | W4: =IF(T4="accept",R4,U4)
A5: c003 | B5: 621 | C5: 283 | D5: 0.566 | E5: 0.5407 | F5: 0.468 | G5: (no heading) (108); information sharing (17); do we disclose any information to outside parties (14) | H5: legal_disclosure_conditions | I5: States that the company may disclose personal information when required by law or to protect rights, property, or safety. | L5: The company discloses personal information when required by law or in good-faith belief that such action is necessary to protect rights or comply with legal processes. | M5: The company may disclose personal information as required by legal process or law. | N5: The company reserves the right to disclose personal information when required by law or to protect its rights. | O5: legal_disclosure (116), legal_compliance (20), legal_sharing (11), legal_release (10), disclosure_reason (9) | P5: c031 0.39, c033 0.34, c072 0.33 | Q5: keep | R5: discloses_when_legally_required | T5: accept | V5: reviewed on the page; see decisions/page_answers_2026-10-15.json and resolutions_2026-10-15.yaml | W5: =IF(T5="accept",R5,U5)
A6: c004 | B6: 586 | C6: 341 | D6: 0.682 | E6: 0.6257 | F6: 0.368 | G6: (no heading) (115); privacy policy (20); california online privacy protection act compliance (12) | H6: no_third_party_sharing | I6: States that the company does not share, sell, rent, or otherwise disclose personal information to third parties without permission or legal requirement. | L6: The company does not sell, rent, or trade personal information to third parties. | M6: The company does not share personal information with non-affiliated third parties without permission. | N6: The company will not share personal information with third parties without permission or legal requirement. | O6: data_sharing_policy (78), data_protection (15), no_third_party_sales (14), data_sharing (14), no_third_party_sharing (13) | P6: c027 0.59, c070 0.54, c043 0.51 | Q6: merge | R6: does_not_sell_or_share | T6: accept | V6: reviewed on the page; see decisions/page_answers_2026-10-15.json and resolutions_2026-10-15.yaml | W6: =IF(T6="accept",R6,U6)
A7: c005 | B7: 528 | C7: 240 | D7: 0.48 | E7: 0.6788 | F7: 0.531 | G7: (no heading) (94); choice opt out (33); your california privacy rights (11) | H7: opt_out_communications | I7: States that the company provides users with the option to opt-out of receiving various types of communications, including emails, direct mailings, and phone calls, from the company and its partners. | L7: The company allows users to opt-out of receiving communications from the company. | M7: The company provides users the opportunity to opt-out of receiving communications from the company and its partners. | N7: The company allows users to opt out of receiving email newsletters by selecting specific links or following opt-out instructions. | O7: opt_out_option (28), user_opt_out (26), opt_out_provision (22), opt_out (17), communication_opt_out (13) | P7: c046 0.81, c035 0.80, c054 0.62 | Q7: merge | R7: opt_out_of_communications | T7: accept | V7: reviewed on the page; see decisions/page_answers_2026-10-15.json and resolutions_2026-10-15.yaml | W7: =IF(T7="accept",R7,U7)
A8: c006 | B8: 463 | C8: 258 | D8: 0.516 | E8: 0.5344 | F8: 0.365 | G8: (no heading) (65); what do we use your information for (18); how we use your information (10) | H8: sends_promotional_emails | I8: States that the company may send promotional emails to users about products, services, and special offers, including newsletters and updates. | L8: The company may send promotional emails about new products or special offers. | M8: The company may send promotional emails to users using the provided email address. | N8: The company may send promotional emails about its products, services, and special offers. | O8: data_use (52), disclosing_practice (23), data_collection (17), email_use (13), marketing_communication (13) | P8: c032 0.67, c045 0.40, c049 0.38 | Q8: merge | R8: sends_marketing_communications | T8: accept | V8: reviewed on the page; see decisions/page_answers_2026-10-15.json and resolutions_2026-10-15.yaml | W8: =IF(T8="accept",R8,U8)
A9: c007 | B9: 444 | C9: 303 | D9: 0.606 | E9: 0.7835 | F9: 0.519 | G9: security (87); (no heading) (69); how do we protect your information (14) | H9: states_security_measures | I9: States that the company has implemented or adopted security measures to protect personal information against unauthorized actions, access, disclosure, alteration, or destruction. | L9: The company has implemented security measures to protect personal information. | M9: The company employs appropriate security measures to protect personal information against unauthorized access, disclosure, alteration, or destruction. | N9: The company uses various security technologies and procedures to protect personal information. | O9: security_measures (149), security_commitment (30), security_procedures (15), data_protection (14), data_protection_commitment (11) | P9: c020 0.78, c065 0.72, c017 0.61 | Q9: keep | R9: states_security_measures | T9: accept | V9: reviewed on the page; see decisions/page_answers_2026-10-15.json and resolutions_2026-10-15.yaml | W9: =IF(T9="accept",R9,U9)
A10: c008 | B10: 440 | C10: 252 | D10: 0.504 | E10: 0.5784 | F10: 0.286 | G10: (no heading) (65); how we use your information (11); personal information (10) | H10: data_use_for_services | I10: States that the company uses collected personal information for providing products, services, processing orders, and customer support. | L10: The company uses collected personal information to provide products and services, process orders, and offer customer service. | M10: The company uses collected information to fulfill orders, provide quotes, process orders, notify about order status, prepare drawings, and provide information about offers or products. | N10: The company uses collected information to deliver requested products and services, manage accounts, and provide customer support. | O10: data_use (81), data_collection_purpose (23), service_provision (22), data_collection (17), data_use_purpose (16) | P10: c028 0.61, c057 0.55, c047 0.45 | Q10: keep | R10: data_use_for_services | T10: accept | V10: reviewed on the page; see decisions/page_answers_2026-10-15.json and resolutions_2026-10-15.yaml | W10: =IF(T10="accept",R10,U10)
A11: c009 | B11: 432 | C11: 263 | D11: 0.526 | E11: 0.672 | F11: 0.605 | G11: (no heading) (65); external links (18); links (18) | H11: disclaim_third_party_responsibility | I11: States that the company is not responsible for the content, practices, policies, or privacy of third-party websites linked from its site. | L11: The company is not responsible for the content, policies, practices, or products of third-party websites. | M11: The company is not responsible for the content, privacy, or security practices of third-party websites. | N11: The company is not responsible for the content or privacy practices of third-party websites linked to its website. | O11: third_party_disclaimer (54), disclaim_responsibility (46), third_party_responsibility (17), liability_disclaimer (15), external_site_disclaimer (12) | P11: c023 0.73, c036 0.60, c064 0.55 | Q11: merge | R11: third_party_sites_and_their_policies | T11: accept | V11: reviewed on the page; see decisions/page_answers_2026-10-15.json and resolutions_2026-10-15.yaml | W11: =IF(T11="accept",R11,U11)
A12: c010 | B12: 430 | C12: 264 | D12: 0.528 | E12: 0.6339 | F12: 0.594 | G12: (no heading) (74); changes to this privacy policy (18); links (16) | H12: advice_on_policy_review | I12: Advises users to review, read, or check the privacy policies of other websites, linked sites, or third-party services, and to stay informed about updates or changes. | L12: The company advises users to review the privacy policies of websites they link to. | M12: The company encourages users to review the privacy policy frequently. | N12: The company advises users to regularly check the privacy policy for changes. | O12: user_advice (22), review_encouragement (15), user_information_link (14), third_party_policy_reference (11), advice_to_users (10) | P12: c018 0.59, c064 0.36, c056 0.34 | Q12: merge | R12: third_party_sites_and_their_policies | T12: accept | V12: reviewed on the page; see decisions/page_answers_2026-10-15.json and resolutions_2026-10-15.yaml | W12: =IF(T12="accept",R12,U12)
A13: c011 | B13: 412 | C13: 266 | D13: 0.532 | E13: 0.5104 | F13: 0.11 | G13: (no heading) (184); privacy policy (30); introduction (8) | H13: policy_coverage | I13: States that the privacy policy covers the collection, use, and handling of personal information, typically specifying the scope of the policy to include the company's websites, services, and sometimes its family of companies. | L13: The company discloses that the privacy policy covers the collection, use, and choices about personal information collected on or through the services. | M13: The company explains the scope of its privacy policy to cover personal information provided through its websites. | N13: The company explains that the privacy policy document describes the personal information collected and its usage. | O13: policy_scope (51), policy_purpose (30), policy_coverage (28), policy_description (23), policy_application (15) | P13: c069 0.47, c063 0.39, c029 0.35 | Q13: keep | R13: policy_coverage | T13: accept | V13: reviewed on the page; see decisions/page_answers_2026-10-15.json and resolutions_2026-10-15.yaml | W13: =IF(T13="accept",R13,U13)
... A16: c014 | B16: 308 | C16: 240 | D16: 0.48 | E16: 0.7074 | F16: 0.645 | G16: (no heading) (67); privacy policy (9); contacting us (9) | H16: provides_contact_method | I16: States that the company provides a contact method for questions, concerns, or suggestions about the privacy policy, data security, or related matters. | L16: The company provides a contact method for questions about the privacy policy or services. | M16: The company provides a contact method for questions about the privacy policy. | N16: The company provides an email address for inquiries or requests about the privacy policy or personal information handling. | O16: contact_method (101), contact_information (97), feedback_welcome (9), contact_provision (8), contact_invitation (6) | P16: c048 0.87, c071 0.67, c032 0.47 | Q16: merge | R16: provides_privacy_contact | T16: accept | V16: reviewed on the page; see decisions/page_answers_2026-10-15.json and resolutions_2026-10-15.yaml | W16: =IF(T16="accept",R16,U16)
A17: c015 | B17: 299 | C17: 249 | D17: 0.498 | E17: 0.8294 | F17: 0.65 | G17: (no heading) (63); changes to this privacy policy (35); changes to our privacy policy (8) | H17: policy_change_right | I17: States that the company reserves the right to change, modify, or update the privacy policy at any time, with or without notice. | J17: example_label_name | L17: The company reserves the right to change the privacy policy at any time. | M17: The company reserves the right to modify the privacy policy at any time. | N17: The company reserves the right to change the privacy policy without notice. | O17: policy_change (39), policy_modification_right (38), policy_change_right (36), policy_modification (31), policy_update (29) | P17: c061 0.79, c056 0.71, c073 0.66 | Q17: keep | R17: reserves_right_to_change_policy | T17: accept | V17: reviewed on the page; see decisions/page_answers_2026-10-15.json and resolutions_2026-10-15.yaml | W17: =IF(T17="accept",R17,U17)
A18: c016 | B18: 286 | C18: 175 | D18: 0.35 | E18: 0.7136 | F18: 0.633 | G18: security (60); (no heading) (57); data security (7) | H18: disclaims_internet_security | I18: States that the company cannot guarantee the security of information transmitted over the internet or wireless networks, often emphasizing the inherent risks and limitations of online transmission. | L18: The company cannot guarantee the security of any information transmitted over the internet. | M18: The company cannot guarantee the security of any information transmitted over the Internet or wireless networks. | N18: The company acknowledges that it cannot guarantee 100% security of information transmitted over the Internet. | O18: security_disclaimer (69), security_limitation (43), security_guarantee (11), transmission_risk (10), security_disclosure (6) | P18: c018 0.49, c007 0.47, c020 0.44 | Q18: keep | R18: security_not_guaranteed | T18: accept | V18: reviewed on the page; see decisions/page_answers_2026-10-15.json and resolutions_2026-10-15.yaml | W18: =IF(T18="accept",R18,U18)
A19: c017 | B19: 283 | C19: 235 | D19: 0.47 | E19: 0.7312 | F19: 0.088 | G19: (no heading) (130); privacy policy (24); privacy statement (7) | H19: privacy_commitment | I19: States that the company is committed to protecting and respecting the privacy and personal information of its users. | L19: The company commits to protecting the privacy and personal information of its users. | M19: The company is committed to protecting and respecting the privacy of individuals. | N19: The company is committed to protecting the privacy of its users. | O19: privacy_commitment (153), commitment_to_privacy (11), protection_commitment (8), privacy_acknowledgment (5), privacy_respect (5) | P19: c007 0.61, c038 0.55, c072 0.55 | Q19: keep | R19: states_policy_scope_and_commitment | T19: accept | V19: reviewed on the page; see decisions/page_answers_2026-10-15.json and resolutions_2026-10-15.yaml | W19: =IF(T19="accept",R19,U19)
A20: c018 | B20: 282 | C20: 152 | D20: 0.304 | E20: 0.6224 | F20: 0.584 | G20: (no heading) (45); security (30); public forums (17) | H20: advises_user_security | I20: Advises users to take specific security measures, such as being cautious with personal information, protecting passwords, and securing accounts, but does not include detailed technical requirements or user responsibilities beyond basic security practices. | L20: The company advises users to be cautious when sharing personal information in public areas of the site. | M20: The company advises users to exercise caution with personal information posted on its websites. | N20: The company advises users to protect their passwords and limit access to their accounts. | O20: security_advice (23), user_responsibility (23), user_advice (19), caution_advice (13), public_disclosure_warning (9) | P20: c010 0.59, c016 0.49, c037 0.40 | Q20: keep | R20: advises_users_on_security | T20: accept | V20: reviewed on the page; see decisions/page_answers_2026-10-15.json and resolutions_2026-10-15.yaml | W20: =IF(T20="accept",R20,U20)
A21: c019 | B21: 282 | C21: 171 | D21: 0.342 | E21: 0.7069 | F21: 0.62 | G21: (no heading) (34); children (29); children s privacy (22) | H21: age_restriction_declaration | I21: States that the company restricts the use of its services or websites to individuals above a certain age, typically 13, and may require parental consent for minors. | L21: The company prohibits the use of its websites or services by anyone under 13 years of age. | M21: The company prohibits anyone under the age of 13 from using the service. | N21: The company states that individuals under 13 should not use the site. | O21: age_restriction (31), target_audience_declaration (11), age_requirement (9), intended_audience (7), data_collection_limit (6) | P21: c041 0.79, c068 0.59, c037 0.44 | Q21: keep | R21: states_minimum_age | T21: accept | V21: reviewed on the page; see decisions/page_answers_2026-10-15.json and resolutions_2026-10-15.yaml | W21: =IF(T21="accept",R21,U21)
A22: c020 | B22: 274 | C22: 164 | D22: 0.328 | E22: 0.7256 | F22: 0.523 | G22: (no heading) (43); security (40); how do we protect your information (20) | H22: uses_ssl_encryption | I22: States that the company uses SSL (Secure Sockets Layer) encryption to secure the transmission of sensitive information, including personally identifiable and credit card information, to prevent unauthorized access. | L22: The company uses SSL to encrypt information transmitted over the Internet. | M22: The company uses Secure Sockets Layer (SSL) encryption for sensitive information to prevent unauthorized access. | N22: The company transmits sensitive information via SSL technology and encrypts it. | O22: encryption_method (35), encryption_use (26), encryption_practice (11), data_encryption (11), encryption_technology (9) | P22: c007 0.78, c065 0.67, c072 0.51 | Q22: keep | R22: encrypts_data_in_transit | T22: accept | V22: reviewed on the page; see decisions/page_answers_2026-10-15.json and resolutions_2026-10-15.yaml | W22: =IF(T22="accept",R22,U22)
A23: c021 | B23: 274 | C23: 175 | D23: 0.35 | E23: 0.5321 | F23: 0.325 | G23: (no heading) (40); information collection and use (9); what information do we collect (7) | H23: registration_information_requirements | I23: States that the company requires users to provide specific personal information during the registration process, including details such as name, email address, and unique identifiers. | L23: The company asks for specific personal information when users register. | M23: The company requires users to provide personal information during registration. | N23: The company requires users to provide a username, password, and email address during registration. | O23: registration_requirement (25), identity_verification (24), data_collection (14), data_request (12), required_information (9) | P23: c002 0.53, c032 0.40, c071 0.32 | Q23: keep | R23: states_information_required_to_register | T23: accept | V23: reviewed on the page; see decisions/page_answers_2026-10-15.json and resolutions_2026-10-15.yaml | W23: =IF(T23="accept",R23,U23)
A24: c022 | B24: 273 | C24: 192 | D24: 0.384 | E24: 0.7148 | F24: 0.502 | G24: (no heading) (48); cookies (44); use of cookies (19) | H24: user_cookie_control | I24: States that users can control cookies through their browser settings, including accepting, declining, disabling, or being notified about cookies. | L24: The company allows users to disable cookies through their web browser settings. | M24: The company allows users to decline cookies by adjusting their browser settings. | N24: The company allows users to accept or decline cookies by modifying their browser settings. | O24: user_control (68), granting_right (16), cookie_control (10), user_cookie_control (10), cookie_use (9) | P24: c034 0.74, c035 0.69, c059 0.49 | Q24: keep | R24: browser_cookie_controls | T24: accept | V24: reviewed on the page; see decisions/page_answers_2026-10-15.json and resolutions_2026-10-15.yaml | W24: =IF(T24="accept",R24,U24)
A25: c023 | B25: 263 | C25: 179 | D25: 0.358 | E25: 0.6302 | F25: 0.59 | G25: (no heading) (34); cookies (18); doubleclick dart cookie (7) | H25: disclaims_control_over_third_party_cookies | I25: States that the company does not have access to, control over, or responsibility for cookies used by third-party advertisers or other third-party services. | L25: The company has no access to or control over cookies used by third-party advertisers. | M25: The company does not have access to or control over the cookies used by third-party advertisers. | N25: The company has no access to or control over cookies used by third-party advertisers. | O25: no_control_over_cookies (18), third_party_control (15), third_party_disclaimer (12), third_party_cookies (7), non_control_third_party (6) | P25: c009 0.73, c039 0.55, c036 0.54 | Q25: keep | R25: disclaims_control_of_third_party_cookies | T25: accept | V25: reviewed on the page; see decisions/page_answers_2026-10-15.json and resolutions_2026-10-15.yaml | W25: =IF(T25="accept",R25,U25)
A26: c024 | B26: 251 | C26: 157 | D26: 0.314 | E26: 0.65 | F26: 0.408 | G26: (no heading) (48); information sharing and disclosure (9); personal information (5) | H26: shares_personal_information_with_third_parties | I26: States that the company shares personal information with third parties for the purpose of performing services, fulfilling orders, or other specific functions on behalf of the company. | L26: The company may share personal information with third parties hired to perform services, under strict conditions. | M26: The company shares personal information with third parties providing services on their behalf. | N26: The company may share personal information with third parties to perform services on behalf of the user. | O26: third_party_sharing (27), data_sharing (20), third_party_disclosure (8), disclosure_to_third_parties (7), third_party_access (7) | P26: c030 0.78, c055 0.65, c044 0.57 | Q26: merge | R26: shares_with_service_providers | T26: accept | V26: reviewed on the page; see decisions/page_answers_2026-10-15.json and resolutions_2026-10-15.yaml | W26: =IF(T26="accept",R26,U26)
A27: c025 | B27: 246 | C27: 111 | D27: 0.222 | E27: 0.4748 | F27: 0.669 | G27: (no heading) (41); arbitration (11); dispute resolution arbitration (9) | H27: legal_governance | I27: States that the privacy policy and related matters are governed by the laws of a specific jurisdiction, including the resolution of disputes and the authoritative version of the policy. | L27: The Privacy Policy is governed by the laws of a specific state. | M27: The company states that the policy and use of the site are governed by New York law. | N27: The company states that disputes over privacy or the privacy policy will be governed by the law of a specific jurisdiction. | O27: term_definition (12), legal_governance (10), dispute_resolution (9), service_location (4), third_party_rights (4) | P27: c036 0.51, c038 0.49, c037 0.46 | Q27: keep | R27: governing_law_and_disputes | T27: accept | V27: reviewed on the page; see decisions/page_answers_2026-10-15.json and resolutions_2026-10-15.yaml | W27: =IF(T27="accept",R27,U27)
A28: c026 | B28: 242 | C28: 132 | D28: 0.264 | E28: 0.5675 | F28: 0.56 | G28: (no heading) (28); data retention (9); retention period (5) | H28: data_retention_policy | I28: States that the company retains personal information for a specified period, typically as long as necessary for the original purpose or as required by law, and may retain it for archival or legal purposes even after account closure. | L28: The company retains personal information as long as necessary for the original purpose or as required by law. | M28: The company retains collected information as long as the user's account is active and as required by legal obligations. | N28: The company may retain personal information for a longer period if required or permitted by law. | O28: data_retention_policy (28), data_retention (23), data_retention_period (18), data_deletion_policy (8), deletion_policy (6) | P28: c065 0.39, c068 0.35, c054 0.33 | Q28: keep | R28: states_retention_period | T28: accept | V28: reviewed on the page; see decisions/page_answers_2026-10-15.json and resolutions_2026-10-15.yaml | W28: =IF(T28="accept",R28,U28)
A29: c027 | B29: 241 | C29: 177 | D29: 0.354 | E29: 0.6535 | F29: 0.354 | G29: (no heading) (39); log files (27); privacy policy (7) | H29: data_non_linking_policy | I29: States that the company does not link collected technical information, such as IP addresses, to personally identifiable information, with some exceptions for compliance or protection. | J29: mixed | K29: data_non_linking_policy, non_identification, data_collection_policy | L29: The company does not link collected IP addresses and other information to personally identifiable information. | M29: The company does not normally link IP addresses to personally identifiable information, but may do so to enforce compliance or protect its service. | N29: The company does not link IP addresses to personally identifiable information. | O29: data_linking_policy (23), non_identification (11), data_collection_policy (8), data_linking (6), data_non_storage (6) | P29: c039 0.67, c062 0.60, c070 0.59 | Q29: merge | R29: tracking_data_not_linked_to_identity | T29: accept | V29: reviewed on the page; see decisions/page_answers_2026-10-15.json and resolutions_2026-10-15.yaml | W29: =IF(T29="accept",R29,U29)
A30: c028 | B30: 231 | C30: 174 | D30: 0.348 | E30: 0.7818 | F30: 0.287 | G30: (no heading) (44); what do we use your information for (29); how do we use your information (10) | H30: uses_data_to_improve_website | I30: States that the company uses collected information to improve the website, services, and user experience. | L30: The company uses collected information to improve the sites and services. | M30: The company uses collected information to improve their website and personalize your experience. | N30: The company uses collected information to improve the website to better serve users. | O30: data_use (53), website_improvement (19), data_collection_purpose (14), service_improvement (14), customer_service_improvement (12) | P30: c057 0.72, c008 0.61, c001 0.42 | Q30: keep | R30: uses_data_to_improve_services | T30: accept | V30: reviewed on the page; see decisions/page_answers_2026-10-15.json and resolutions_2026-10-15.yaml | W30: =IF(T30="accept",R30,U30)
A31: c029 | B31: 230 | C31: 186 | D31: 0.372 | E31: 0.6117 | F31: 0.37 | G31: (no heading) (66); changes to our privacy policy (10); privacy policy (8) | H31: consent_through_use | I31: States that using the website or service implies or signifies the user's consent to the privacy policy or the collection and use of their information. | L31: The company states that using the site implies consent to the privacy policy. | M31: The company states that by using the site, users signify their acceptance of the privacy policy. | N31: The company states that by using the Services, users consent to the collection and use of their information as outlined in the Privacy Policy. | O31: user_consent (36), user_agreement (24), consent_implied (12), consent_through_use (11), user_acceptance (11) | P31: c073 0.50, c037 0.38, c011 0.35 | Q31: keep | R31: consent_by_use | T31: accept | V31: reviewed on the page; see decisions/page_answers_2026-10-15.json and resolutions_2026-10-15.yaml | W31: =IF(T31="accept",R31,U31)
A32: c030 | B32: 228 | C32: 155 | D32: 0.31 | E32: 0.6526 | F32: 0.388 | G32: (no heading) (42); privacy policy (5); use of information collected (4) | H32: shares_information_with_affiliates_partners | I32: States that the company may share personal information with affiliates, subsidiaries, business partners, or related entities for various business purposes, including fulfilling requests, marketing, and operational needs. | L32: The company may share personal information with business partners to fulfill requests for products or services. | M32: The company states that personal information may be shared with partners providing services on their behalf. | N32: The company shares personal information with other entities and affiliates within the family of companies for business and operational purposes. | O32: data_sharing (36), data_sharing_purpose (9), information_sharing (8), affiliate_sharing (6), disclosure_to_affiliates (5) | P32: c024 0.78, c044 0.63, c033 0.49 | Q32: keep | R32: shares_with_affiliates_and_partners | T32: accept | V32: reviewed on the page; see decisions/page_answers_2026-10-15.json and resolutions_2026-10-15.yaml | W32: =IF(T32="accept",R32,U32)
A33: c031 | B33: 215 | C33: 95 | D33: 0.19 | E33: 0.4998 | F33: 0.692 | G33: (no heading) (16); privacy complaints (9); rights of the parties concerned (9) | H33: disclose_data_rights | I33: States that the company informs users of their rights to access, complain, or request changes to their personal data held by the company. | L33: The company allows individuals to complain to a data protection authority about their collection and use of personal information. | M33: The company discloses that individuals have the right to raise a complaint with the data protection regulator. | N33: The company discloses that individuals have the right to request access to, deletion of, or correction of their personal data held by the company. | O33: disclose_right (30), access_right (11), disclose_rights (11), complaint_right (5), data_access_right (4) | P33: c014 0.46, c012 0.43, c003 0.39 | Q33: keep | R33: disclose_data_rights | T33: accept | V33: reviewed on the page; see decisions/page_answers_2026-10-15.json and resolutions_2026-10-15.yaml | W33: =IF(T33="accept",R33,U33)
A34: c032 | B34: 213 | C34: 152 | D34: 0.304 | E34: 0.6598 | F34: 0.382 | G34: (no heading) (43); personal information (9); registration (6) | H34: uses_contact_information | I34: States that the company uses contact information to communicate with users about products, services, promotions, and administrative matters, but not for marketing unless consent is given. | L34: The company uses information to contact users about relevant services and offers. | M34: The company uses personal information to contact users about products, services, upcoming events, and offers from itself and third parties. | N34: The company uses contact information to communicate about administrative notices, new product offerings, and relevant communications. | O34: data_use (30), contact_use (13), disclosing_practice (7), data_use_purpose (7), communication_purpose (6) | P34: c006 0.67, c071 0.60, c048 0.49 | Q34: merge | R34: sends_marketing_communications | T34: accept | V34: reviewed on the page; see decisions/page_answers_2026-10-15.json and resolutions_2026-10-15.yaml | W34: =IF(T34="accept",R34,U34)
A35: c033 | B35: 206 | C35: 148 | D35: 0.296 | E35: 0.6907 | F35: 0.502 | G35: (no heading) (27); business transfers (11); sharing information (5) | H35: business_transfer_data | I35: States that the company may transfer personal information to third parties in the event of a business transaction such as a merger, acquisition, sale, or reorganization, but does not include routine data sharing or transfers for operational purposes. | L35: The company may transfer personal information to an acquiring or merging party as part of a business transaction. | M35: The company may transfer personal information as part of a merger, acquisition, or sale of assets. | N35: The company may transfer personal information to a third party in the event of a merger, acquisition, reorganization, or sale of assets. | O35: business_transfer (13), data_transfer (9), asset_transfer (5), business_transfer_disclosure (4), data_transfer_on_acquisition (4) | P35: c040 0.50, c030 0.49, c024 0.48 | Q35: keep | R35: transfers_data_in_business_transfer | T35: accept | V35: reviewed on the page; see decisions/page_answers_2026-10-15.json and resolutions_2026-10-15.yaml | W35: =IF(T35="accept",R35,U35)
A36: c034 | B36: 200 | C36: 169 | D36: 0.338 | E36: 0.7751 | F36: 0.464 | G36: (no heading) (44); cookies (32); use of cookies (11) | H36: disabling_cookies_consequences | I36: Warns that disabling cookies may affect the functionality, access to features, or performance of the website. | L36: The company notes that refusing cookies may affect the functionality of the website. | M36: Disabling cookies may prevent some parts of the website from operating correctly and may limit access to some features or services. | N36: You are always free to decline any cookies we use by adjusting the settings of your browser, but some products, services or features might not be available or operate properly if cookies are not enabled. | O36: stating_limitation (13), user_control (9), disabling_consequence (7), functionality_warning (7), cookie_disabling (6) | P36: c022 0.74, c035 0.56, c053 0.40 | Q36: keep | R36: warns_disabling_cookies_limits_site | T36: accept | V36: reviewed on the page; see decisions/page_answers_2026-10-15.json and resolutions_2026-10-15.yaml | W36: =IF(T36="accept",R36,U36)
A37: c035 | B37: 195 | C37: 124 | D37: 0.248 | E37: 0.6993 | F37: 0.566 | G37: (no heading) (20); doubleclick dart cookie (18); cookies (10) | H37: provides_opt_out_options | I37: States that the company provides users with various options to opt out of specific types of data collection or advertising, including links, methods, and instructions for opting out of cookies, interest-based advertising, and mobile tracking. | L37: The company provides a way for users to opt out of the DART cookie use. | M37: Users may opt out of the use of the DART cookie by visiting the advertising opt-out page. | N37: The company provides a link for users to opt out of interest-based advertising using the DoubleClick cookie. | O37: user_opt_out (25), opt_out_provision (22), opt_out_link (18), dart_cookie_opt_out (12), granting_right (10) | P37: c005 0.80, c022 0.69, c046 0.59 | Q37: keep | R37: opt_out_of_tracking_or_ads | T37: accept | V37: reviewed on the page; see decisions/page_answers_2026-10-15.json and resolutions_2026-10-15.yaml | W37: =IF(T37="accept",R37,U37)
A38: c036 | B38: 193 | C38: 148 | D38: 0.296 | E38: 0.692 | F38: 0.449 | G38: (no heading) (42); links (11); online privacy policy only (11) | H38: policy_scope_limitation | I38: States that the company's privacy policy applies only to its own website and not to other linked, external, or third-party websites or services. | L38: The company's privacy policy applies only to its own website and not to other linked websites. | M38: The company's privacy policy does not apply to external websites. | N38: The company's privacy policy does not apply to third-party websites or services. | O38: policy_scope (49), policy_exclusion (23), policy_non_applicability (10), policy_coverage_limitation (7), policy_limitation (6) | P38: c009 0.60, c064 0.55, c023 0.54 | Q38: keep | R38: scope_excludes_third_party_sites | T38: accept | V38: reviewed on the page; see decisions/page_answers_2026-10-15.json and resolutions_2026-10-15.yaml | W38: =IF(T38="accept",R38,U38)
A39: c037 | B39: 184 | C39: 103 | D39: 0.206 | E39: 0.4466 | F39: 0.589 | G39: (no heading) (54); terms and services bookplate creator (6); social media disclaimer (5) | H39: content_and_usage_restrictions | I39: States that users must not use the site or its content in certain ways, including reproducing, modifying, or distributing content without permission, and must not use the site if they do not agree to the terms or privacy policy. | J39: mixed | K39: content_restriction, disagreement_consequence | L39: The company states that users are not allowed to submit content that violates or infringes the rights of others. | M39: The company states that users may not modify, copy, reproduce, create derivative works, republish, display, upload, post, transmit, or distribute content without prior written consent. | N39: The company states that if users do not agree with the terms, they should not use the site. | O39: disagreement_action (8), ownership_claim (8), content_restriction (7), disagreement_consequence (5), content_ownership (4) | P39: c025 0.46, c019 0.44, c018 0.40 | Q39: keep | R39: content_and_usage_restrictions | T39: accept | V39: reviewed on the page; see decisions/page_answers_2026-10-15.json and resolutions_2026-10-15.yaml | W39: =IF(T39="accept",R39,U39)
A40: c038 | B40: 180 | C40: 114 | D40: 0.228 | E40: 0.56 | F40: 0.497 | G40: (no heading) (40); childrens online privacy protection act compliance (10); california online privacy protection act compliance (7) | H40: compliance_with_laws_and_standards | I40: States that the company complies with specific laws, regulations, or industry standards related to privacy and data protection. | L40: The company participates in and has certified compliance with the EU-U.S. Privacy Shield Framework. | M40: The company complies with the Children's Online Privacy Protection Act and all other applicable laws. | N40: The company operates its website in compliance with the Children's Online Privacy Protection Act (COPPA). | O40: compliance_statement (15), legal_compliance (15), compliance_with_law (5), safe_harbor_principles (5), third_party_seal (5) | P40: c017 0.55, c025 0.49, c007 0.47 | Q40: keep | R40: complies_with_laws_and_programs | T40: accept | V40: reviewed on the page; see decisions/page_answers_2026-10-15.json and resolutions_2026-10-15.yaml | W40: =IF(T40="accept",R40,U40)
A41: c039 | B41: 180 | C41: 144 | D41: 0.288 | E41: 0.7122 | F41: 0.42 | G41: (no heading) (38); cookies (34); log files (8) | H41: cookie_non_identification | I41: States that the company does not use cookies to collect, store, or link to personally identifiable information. | L41: The company does not use cookies to collect personally identifiable information. | M41: The company does not use cookies to collect users' personally identifiable information. | N41: The company states that cookies do not collect personally identifiable information. | O41: stating_limitation (10), cookie_policy (10), cookie_usage (9), cookie_use (9), cookie_limitation (7) | P41: c027 0.67, c023 0.55, c062 0.53 | Q41: merge | R41: tracking_data_not_linked_to_identity | T41: accept | V41: reviewed on the page; see decisions/page_answers_2026-10-15.json and resolutions_2026-10-15.yaml | W41: =IF(T41="accept",R41,U41)
A42: c040 | B42: 176 | C42: 101 | D42: 0.202 | E42: 0.6656 | F42: 0.584 | G42: (no heading) (18); international transfer (6); where we store your personal data (5) | H42: data_transfer_to_us | I42: States that personal information may be transferred to, stored, or processed in the United States, often requiring user consent or agreement. | L42: The company states that personal information may be transferred to, stored, or processed in the USA. | M42: Personal data provided by users outside the United States will be transferred to the United States. | N42: The company may store and process collected information in any of the countries where it operates. | O42: data_transfer (39), data_storage_location (15), data_location (11), data_processing_location (7), user_consent (6) | P42: c033 0.50, c024 0.27, c030 0.23 | Q42: keep | R42: transfers_data_internationally | T42: accept | V42: reviewed on the page; see decisions/page_answers_2026-10-15.json and resolutions_2026-10-15.yaml | W42: =IF(T42="accept",R42,U42)
A43: c041 | B43: 173 | C43: 155 | D43: 0.31 | E43: 0.847 | F43: 0.59 | G43: (no heading) (26); children s privacy (18); children (15) | H43: no_child_data_collection | I43: States that the company does not knowingly collect personal information from children under a certain age, typically 13. | L43: The company does not knowingly collect personal information from children under 13. | M43: The company does not knowingly collect, use, or disclose personal information from children under the age of 13. | N43: The company does not knowingly collect personal information from children under the age of 13. | O43: data_collection_policy (40), data_collection_restriction (21), no_child_data_collection (19), no_collection_under_age (9), data_collection_limitation (6) | P43: c019 0.79, c068 0.61, c027 0.53 | Q43: keep | R43: no_knowing_collection_from_children | T43: accept | V43: reviewed on the page; see decisions/page_answers_2026-10-15.json and resolutions_2026-10-15.yaml | W43: =IF(T43="accept",R43,U43)
A44: c042 | B44: 170 | C44: 105 | D44: 0.21 | E44: 0.777 | F44: 0.57 | G44: doubleclick dart cookie (29); cookies (17); what information do we collect (12) | H44: third_party_ad_cookie_use | I44: States that third parties, such as Google, use cookies to serve ads based on users' visits to the company's site and other sites. | L44: A third party vendor, such as Google, uses cookies to serve ads on the site. | M44: Google uses cookies to serve ads based on users' visits to this and other sites. | N44: The company notes that some ads may be served by Google using the DART cookie. | O44: third_party_cookie_use (24), disclosing_practice (18), cookie_usage (13), dart_cookie_use (11), cookie_function (9) | P44: c053 0.74, c049 0.73, c000 0.58 | Q44: merge | R44: third_party_advertising_and_cookies | T44: accept | V44: reviewed on the page; see decisions/page_answers_2026-10-15.json and resolutions_2026-10-15.yaml | W44: =IF(T44="accept",R44,U44)
A45: c043 | B45: 167 | C45: 123 | D45: 0.246 | E45: 0.575 | F45: 0.45 | G45: (no heading) (32); privacy policy (5); the way we use information (5) | H45: no_email_sharing_policy | I45: States that the company does not sell, share, or rent users' email addresses to third parties, with possible exceptions for legal requirements or user consent. | L45: The company does not sell, trade, share, or rent the user's email address to anyone. | M45: The company does not sell, trade, share, or rent the email address of its customers. | N45: The company does not sell or disclose email addresses to third parties. | O45: data_sharing_policy (10), data_use (6), data_sharing (5), data_use_limitation (5), email_sharing_policy (4) | P45: c027 0.51, c004 0.51, c070 0.51 | Q45: merge | R45: does_not_sell_or_share | T45: accept | V45: reviewed on the page; see decisions/page_answers_2026-10-15.json and resolutions_2026-10-15.yaml | W45: =IF(T45="accept",R45,U45)
A46: c044 | B46: 165 | C46: 130 | D46: 0.26 | E46: 0.6305 | F46: 0.382 | G46: (no heading) (37); non personal information (6); privacy policy (5) | H46: shares_aggregated_data | I46: States that the company may share aggregated, non-personally identifiable information with third parties, business partners, affiliates, and advertisers for various purposes, including marketing, research, and business analysis. | L46: The company may share aggregated non-personally identifiable demographic information with third parties. | M46: The company may share aggregated demographic information not linked to personal identification with business partners, affiliates, and advertisers. | N46: The company may share aggregated, non-personal information with third parties. | O46: data_sharing (39), aggregate_data_sharing (11), aggregated_data_sharing (8), aggregate_sharing (4), data_use (4) | P46: c030 0.63, c024 0.57, c049 0.43 | Q46: keep | R46: shares_aggregated_data | T46: accept | V46: reviewed on the page; see decisions/page_answers_2026-10-15.json and resolutions_2026-10-15.yaml | W46: =IF(T46="accept",R46,U46)
A47: c045 | B47: 161 | C47: 104 | D47: 0.208 | E47: 0.5919 | F47: 0.374 | G47: (no heading) (26); surveys and contests (12); official rules (7) | H47: data_collection_contests_surveys | I47: States that the company collects personal information from users through contests, surveys, and other similar activities on their website. | L47: The company collects information when users participate in contests or promotions. | M47: The company collects personal information when you participate in contests, promotions, or sweepstakes on their websites. | N47: The company collects information from surveys, contests, and sweepstakes. | O47: data_collection (9), data_use (7), data_use_purpose (6), survey_conduct (6), site_feature_administration (3) | P47: c006 0.40, c032 0.39, c002 0.33 | Q47: keep | R47: data_collection_contests_surveys | T47: accept | V47: reviewed on the page; see decisions/page_answers_2026-10-15.json and resolutions_2026-10-15.yaml | W47: =IF(T47="accept",R47,U47)
A48: c046 | B48: 148 | C48: 104 | D48: 0.208 | E48: 0.7932 | F48: 0.55 | G48: (no heading) (13); what do we use your information for (10); mailing lists (6) | H48: provides_unsubscribe_option | I48: States that the company provides users with the option to unsubscribe from receiving emails, newsletters, or promotional communications, often including specific methods or instructions for doing so. | L48: The company allows users to unsubscribe from receiving future emails. | M48: The company allows users to unsubscribe from email newsletters at any time via a link in the newsletter. | N48: The company allows users to unsubscribe by using a link at the bottom of each email. | O48: unsubscribe_option (34), unsubscribe_method (7), unsubscribe_instructions (7), grant_right (5), unsubscribe_provision (5) | P48: c005 0.81, c054 0.67, c035 0.59 | Q48: merge | R48: opt_out_of_communications | T48: accept | V48: reviewed on the page; see decisions/page_answers_2026-10-15.json and resolutions_2026-10-15.yaml | W48: =IF(T48="accept",R48,U48)
A49: c047 | B49: 139 | C49: 75 | D49: 0.15 | E49: 0.4994 | F49: 0.455 | G49: (no heading) (26); india (21); s definitions (6) | H49: company_identification_and_service_definition | I49: States that the company identifies itself, its affiliates, or subsidiaries, and defines the services, products, or terms related to its operations. | J49: mixed | K49: company_identification, definition_of_terms | L49: The company identifies itself as the owner and operator of the website or online service. | M49: The company defines the term 'Services' to include the websites, applications, and community features operated by the company. | N49: The company defines the term 'Affiliates' to include subsidiaries and entities with an ownership interest. | O49: service_offering (13), company_identification (7), data_controller (6), service_description (5), definition_of_terms (4) | P49: c055 0.46, c008 0.45, c058 0.37 | Q49: keep | R49: company_identification_and_service_definition | T49: accept | V49: reviewed on the page; see decisions/page_answers_2026-10-15.json and resolutions_2026-10-15.yaml | W49: =IF(T49="accept",R49,U49)
A50: c048 | B50: 137 | C50: 130 | D50: 0.26 | E50: 0.8902 | F50: 0.827 | G50: contacting us (27); (no heading) (20); how to contact us (9) | H50: provides_contact_information | I50: States that the company provides contact information for questions, concerns, or inquiries about the privacy policy, practices, or related matters. | J50: duplicate_name | L50: The company provides contact information for questions about privacy policy or practices. | M50: The company provides contact information for questions or concerns about the privacy policy or information practices. | N50: The company provides contact details for inquiries about the privacy statement, site practices, or user interactions. | O50: contact_information (124), contact_information_provision (5), contact_details (3), contact_information_provided (2), complaint_contact (1) | P50: c014 0.87, c071 0.85, c032 0.49 | Q50: merge | R50: provides_privacy_contact | T50: accept | V50: reviewed on the page; see decisions/page_answers_2026-10-15.json and resolutions_2026-10-15.yaml | W50: =IF(T50="accept",R50,U50)
A51: c049 | B51: 130 | C51: 101 | D51: 0.202 | E51: 0.6998 | F51: 0.44 | G51: (no heading) (23); third party advertising (15); advertising (7) | H51: third_party_ad_targeting | I51: States that third-party companies use information about website visits to provide targeted advertisements, often specifying that the information is non-personal or non-personally identifiable. | L51: Third-party companies may use information about visits to provide targeted advertisements. | M51: Third-party advertising companies may use aggregated information about visits to provide targeted advertisements. | N51: Third-party companies may use information about visits to the website and other sites to provide targeted advertisements, excluding personal contact information. | O51: data_use (12), advertising_use (12), third_party_advertising (8), third_party_data_use (6), ad_targeting (6) | P51: c042 0.73, c058 0.66, c053 0.47 | Q51: merge | R51: third_party_advertising_and_cookies | T51: accept | V51: reviewed on the page; see decisions/page_answers_2026-10-15.json and resolutions_2026-10-15.yaml | W51: =IF(T51="accept",R51,U51)
A52: c050 | B52: 126 | C52: 68 | D52: 0.136 | E52: 0.6645 | F52: 0.406 | G52: (no heading) (16); aggregated anonymized or statistical information (7); cookies and web beacons (7) | H52: uses_tracking_technologies | I52: States that the company uses cookies, web beacons, and other tracking technologies to collect and store information about user behavior and preferences. | L52: The company uses cookies and similar tracking technologies to access or store information. | M52: The company uses cookies and other tracking technologies to collect and store information. | N52: The company and its partners use cookies, web beacons, and similar tracking technologies on their websites and mobile applications. | O52: technology_use (13), data_collection (10), data_collection_method (9), disclosing_practice (5), tracking_technology_use (5) | P52: c000 0.69, c053 0.56, c052 0.56 | Q52: merge | R52: uses_cookies | T52: accept | V52: reviewed on the page; see decisions/page_answers_2026-10-15.json and resolutions_2026-10-15.yaml | W52: =IF(T52="accept",R52,U52)
A53: c051 | B53: 124 | C53: 106 | D53: 0.212 | E53: 0.7097 | F53: 0.522 | G53: (no heading) (23); security (20); how do we protect your information (8) | H53: access_restriction | I53: States that the company restricts access to personal information to only those individuals who have a specific business need to know or perform their duties. | L53: The company restricts access to personal information to only those personnel who need it for business activities. | M53: The company limits access to personal information to employees, agents, and contractors with a business need to know. | N53: The company limits access to Personal Information to only those employees who need it to perform their duties. | O53: access_restriction (34), access_limitation (15), access_control (12), data_access_control (5), data_use_limitation (4) | P53: c065 0.57, c072 0.48, c004 0.46 | Q53: merge | R53: limits_internal_access | T53: accept | V53: reviewed on the page; see decisions/page_answers_2026-10-15.json and resolutions_2026-10-15.yaml | W53: =IF(T53="accept",R53,U53)
A54: c052 | B54: 118 | C54: 67 | D54: 0.134 | E54: 0.6932 | F54: 0.435 | G54: (no heading) (19); web beacons (8); use of web beacons or gif files (7) | H54: web_beacon_data_collection | I54: States that the company uses web beacons, pixel tags, or similar technologies to collect data about user interactions, site visits, and email opens for analytics and performance measurement. | L54: The company uses web beacons to track user visits and email opens for analytics purposes. | M54: The company uses web beacons to track which visitors interact with specific elements on web pages or emails. | N54: The company uses pixel tags and web beacons to track user actions on the Website and in emails. | O54: web_beacon_use (14), disclosing_practice (13), data_collection_method (11), email_tracking (9), data_collection (8) | P54: c001 0.63, c050 0.56, c000 0.50 | Q54: keep | R54: uses_web_beacons | T54: accept | V54: reviewed on the page; see decisions/page_answers_2026-10-15.json and resolutions_2026-10-15.yaml | W54: =IF(T54="accept",R54,U54)
A55: c053 | B55: 118 | C55: 104 | D55: 0.208 | E55: 0.7212 | F55: 0.523 | G55: doubleclick dart cookie (17); (no heading) (14); cookies (11) | H55: discloses_third_party_cookie_use | I55: States that third-party advertising partners, services, or companies may use cookies or web beacons on the company's website to collect information or serve advertisements. | L55: The company mentions that third-party advertising and marketing partners may use their own cookies. | M55: Third-party advertising companies may use cookies when serving content and advertisements on the website. | N55: The company mentions that some advertising partners may use cookies and web beacons on the site. | O55: partner_cookie_use (10), third_party_cookie_use (8), advertising_partner (8), third_party_data_collection (7), disclosing_practice (7) | P55: c042 0.74, c000 0.61, c050 0.56 | Q55: merge | R55: third_party_advertising_and_cookies | T55: accept | V55: reviewed on the page; see decisions/page_answers_2026-10-15.json and resolutions_2026-10-15.yaml | W55: =IF(T55="accept",R55,U55)
A56: c054 | B56: 114 | C56: 89 | D56: 0.178 | E56: 0.7095 | F56: 0.634 | G56: choice opt out (15); (no heading) (13); content removal (3) | H56: data_removal_option | I56: States that the company provides users with the option to request the removal or deletion of their personal information from the company's database or systems. | L56: The company allows users to request the removal of their personal information at any time. | M56: The company provides options for users to remove their information from its database. | N56: The company provides a method for users to request the removal of their personal information. | O56: data_removal_option (9), data_removal (5), account_deletion (4), removal_right (3), deletion_request (3) | P56: c046 0.67, c005 0.62, c012 0.55 | Q56: keep | R56: deletion_on_request | T56: accept | V56: reviewed on the page; see decisions/page_answers_2026-10-15.json and resolutions_2026-10-15.yaml | W56: =IF(T56="accept",R56,U56)
A57: c055 | B57: 113 | C57: 92 | D57: 0.184 | E57: 0.6905 | F57: 0.467 | G57: (no heading) (14); service providers (3); privacy policy (3) | H57: uses_third_party_services | I57: States that the company uses third-party service providers to perform various functions, provide services, or process information on its behalf. | L57: The company uses third party service providers to perform various functions on its behalf. | M57: The company uses third parties to perform services on its behalf. | N57: The company uses third-party services to support the operation of its service. | O57: third_party_use (25), third_party_services (20), third_party_service (4), third_party_processing (4), third_party_function (2) | P57: c058 0.77, c024 0.65, c066 0.50 | Q57: merge | R57: shares_with_service_providers | T57: accept | V57: reviewed on the page; see decisions/page_answers_2026-10-15.json and resolutions_2026-10-15.yaml | W57: =IF(T57="accept",R57,U57)
A58: c056 | B58: 111 | C58: 99 | D58: 0.198 | E58: 0.857 | F58: 0.761 | G58: changes to this privacy policy (22); (no heading) (15); changes to our privacy policy (6) | H58: notifies_of_policy_changes | I58: States that the company will notify users of material changes to the privacy policy, often specifying methods such as email or a notice on the website. | J58: example_label_name | L58: The company will notify users of material changes to the privacy policy. | M58: The company will notify users of material changes to the privacy policy by email or a notice on the site. | N58: The company will notify users of material changes by email or by prominently posting notice on their website. | O58: notification_method (21), policy_change_notification (13), material_change_notification (12), notification_of_changes (12), notification_commitment (7) | P58: c061 0.82, c067 0.73, c015 0.71 | Q58: merge | R58: states_how_changes_are_notified | T58: accept | V58: reviewed on the page; see decisions/page_answers_2026-10-15.json and resolutions_2026-10-15.yaml | W58: =IF(T58="accept",R58,U58)
A59: c057 | B59: 111 | C59: 98 | D59: 0.196 | E59: 0.7407 | F59: 0.297 | G59: (no heading) (18); what do we use your information for (14); how do we use your information (4) | H59: personalization_data_use | I59: States that the company uses collected information to personalize the user experience, content, and product offerings. | L59: The company uses data to personalize and tailor the user experience and products. | M59: The company uses collected information to personalize the user experience. | N59: The company uses collected information to personalize the user experience. | O59: data_use (27), personalization_use (23), data_use_purpose (6), personalization (5), information_use (3) | P59: c028 0.72, c008 0.55, c000 0.43 | Q59: keep | R59: uses_data_to_personalize | T59: accept | V59: reviewed on the page; see decisions/page_answers_2026-10-15.json and resolutions_2026-10-15.yaml | W59: =IF(T59="accept",R59,U59)
A60: c058 | B60: 109 | C60: 95 | D60: 0.19 | E60: 0.7899 | F60: 0.535 | G60: (no heading) (19); third party advertising (12); cookies (6) | H60: uses_third_party_advertising | I60: States that the company uses third-party advertising companies to serve, display, or present ads on its website or other sites. | L60: The company uses third-party advertising companies to serve ads on other websites. | M60: The company uses third-party advertising companies to serve ads on its website. | N60: The company uses third-party advertising companies to serve ads based on visits to the website and others. | O60: third_party_advertising (29), third_party_use (16), third_party_ads (12), disclosing_practice (3), third_party_ad_usage (3) | P60: c055 0.77, c049 0.66, c066 0.57 | Q60: merge | R60: third_party_advertising_and_cookies | T60: accept | V60: reviewed on the page; see decisions/page_answers_2026-10-15.json and resolutions_2026-10-15.yaml | W60: =IF(T60="accept",R60,U60)
A61: c059 | B61: 108 | C61: 87 | D61: 0.174 | E61: 0.6326 | F61: 0.413 | G61: (no heading) (24); marketing communications (4); notification of changes (3) | H61: user_control_over_information | I61: States that the company provides users with choices and control over their personal information, including the ability to decide what information to provide, how it is used, and the ability to modify preferences and settings. | L61: The company allows users to choose whether to provide personal information. | M61: The company allows users to control their personal information as they see fit. | N61: The company reports that users can change their information at any time through their control panel. | O61: user_control (17), choice_explanation (5), user_choices (4), user_preference_change (3), user_choice (3) | P61: c012 0.58, c005 0.51, c022 0.49 | Q61: merge | R61: information_provision_is_optional | T61: accept | V61: reviewed on the page; see decisions/page_answers_2026-10-15.json and resolutions_2026-10-15.yaml | W61: =IF(T61="accept",R61,U61)
A62: c060 | B62: 102 | C62: 89 | D62: 0.178 | E62: 0.7603 | F62: 0.331 | G62: log files (34); (no heading) (6); information we collect and how we use it (3) | H62: log_file_data_collection | I62: States that the company uses log files to collect various types of data for purposes such as analyzing trends, administering the site, tracking user movement, and gathering demographic information. | L62: The company uses log files to collect various types of data for analyzing trends, administering the site, tracking user movement, and gathering demographic information. | M62: The company uses log files to collect various types of data for analyzing trends and administering the site. | N62: The company uses log files to collect information such as IP addresses, browser type, ISP, date/time stamp, referring/exit pages, and number of clicks. | O62: data_collection (35), data_collection_purpose (11), log_file_collection (3), data_collection_method (3), data_use (3) | P62: c001 0.73, c002 0.46, c008 0.41 | Q62: merge | R62: collects_usage_data_automatically | T62: accept | V62: reviewed on the page; see decisions/page_answers_2026-10-15.json and resolutions_2026-10-15.yaml | W62: =IF(T62="accept",R62,U62)
A63: c061 | B63: 97 | C63: 91 | D63: 0.182 | E63: 0.8603 | F63: 0.804 | G63: changes to our privacy policy (16); changes to this privacy policy (12); (no heading) (12) | H63: policy_change_notification | I63: States that the company will post any changes to the privacy policy on their website, often specifying the location such as the homepage or a specific page. | J63: example_label_name | L63: The company will post any changes to the privacy policy on their website. | M63: The company will post changes to its privacy policy on its Homepage. | N63: The company will post changes to its privacy policy on its website homepage. | O63: policy_change_notification (25), commitment_to_post_changes (12), policy_update_notification (9), policy_update_method (4), policy_change_announcement (3) | P63: c056 0.82, c015 0.79, c073 0.67 | Q63: merge | R63: states_how_changes_are_notified | T63: accept | V63: reviewed on the page; see decisions/page_answers_2026-10-15.json and resolutions_2026-10-15.yaml | W63: =IF(T63="accept",R63,U63)
A64: c062 | B64: 97 | C64: 85 | D64: 0.17 | E64: 0.6828 | F64: 0.208 | G64: (no heading) (23); what information do we collect (14); personal information (4) | H64: allows_anonymous_visit | I64: States that users can visit the site or use its services without providing personal information or registering. | L64: The company allows users to visit the site without providing personal information. | M64: The company states that visitors can use the site anonymously without revealing personal data. | N64: The company discloses that users can use the website without providing personal information. | O64: anonymous_visit (23), no_personal_info_required (8), no_information_required (4), anonymity_option (3), no_disclosure_required (3) | P64: c027 0.60, c039 0.53, c070 0.33 | Q64: merge | R64: information_provision_is_optional | T64: accept | V64: reviewed on the page; see decisions/page_answers_2026-10-15.json and resolutions_2026-10-15.yaml | W64: =IF(T64="accept",R64,U64)
A65: c063 | B65: 95 | C65: 79 | D65: 0.158 | E65: 0.8156 | F65: 0.537 | G65: (no heading) (30); changes to this policy (4); changes to this privacy policy (4) | H65: states_policy_update_date | I65: States the date when the privacy policy was last updated, revised, or became effective. | L65: The company indicates the last update date of the privacy policy. | M65: The company states the date when the privacy policy was last updated. | N65: The company specifies the effective date of the policy. | O65: policy_update_date (22), policy_effective_date (22), update_date (4), effective_date (4), policy_revision_date (3) | P65: c015 0.59, c061 0.59, c056 0.49 | Q65: keep | R65: states_last_updated_date | T65: accept | V65: reviewed on the page; see decisions/page_answers_2026-10-15.json and resolutions_2026-10-15.yaml | W65: =IF(T65="accept",R65,U65)
A66: c064 | B66: 95 | C66: 74 | D66: 0.148 | E66: 0.6577 | F66: 0.505 | G66: (no heading) (20); third party websites (6); third party links (5) | H66: states_third_party_policies | I66: States that third-party websites, services, or affiliates have their own privacy policies, which may differ from the company's own policy. | L66: The company states that third-party sites have separate and independent privacy policies. | M66: Third-party websites and services may have their own privacy policies. | N66: The company notes that linked websites may have different privacy policies and may collect information differently. | O66: third_party_policy (10), third_party_policies (10), third_party_links (7), third_party_privacy_policy (4), third_party_terms (3) | P66: c066 0.60, c036 0.55, c009 0.55 | Q66: merge | R66: third_party_sites_and_their_policies | T66: accept | V66: reviewed on the page; see decisions/page_answers_2026-10-15.json and resolutions_2026-10-15.yaml | W66: =IF(T66="accept",R66,U66)
A67: c065 | B67: 95 | C67: 80 | D67: 0.16 | E67: 0.6902 | F67: 0.556 | G67: security (15); (no heading) (10); confidentiality and security (4) | H67: data_storage_security | I67: States that the company stores personal information in secure environments, typically using password protection, firewalls, and other security measures. | L67: The company stores personal information in secured and password-protected databases. | M67: The company stores information in a database that is secured with a firewall and password protection. | N67: The company stores personal information on secure password and firewall protected servers. | O67: data_storage (15), data_storage_security (8), secure_storage (7), password_protection (7), data_protection (6) | P67: c007 0.72, c020 0.67, c051 0.57 | Q67: keep | R67: stores_data_securely | T67: accept | V67: reviewed on the page; see decisions/page_answers_2026-10-15.json and resolutions_2026-10-15.yaml | W67: =IF(T67="accept",R67,U67)
A68: c066 | B68: 94 | C68: 80 | D68: 0.16 | E68: 0.7501 | F68: 0.629 | G68: (no heading) (14); links (9); links to other sites (7) | H68: provides_third_party_links | I68: States that the company includes or provides links to third-party websites, often advising users to review the privacy policies of those sites. | L68: The company includes links to third-party sites on its website. | M68: The company provides links to other websites. | N68: The company provides links to other sites on their web site, and advises users to review privacy policies on those sites. | O68: third_party_links (23), provides_links (7), link_disclosure (6), link_inclusion (6), provision_of_links (3) | P68: c064 0.60, c058 0.57, c055 0.50 | Q68: keep | R68: provides_third_party_links | T68: accept | V68: reviewed on the page; see decisions/page_answers_2026-10-15.json and resolutions_2026-10-15.yaml | W68: =IF(T68="accept",R68,U68)
A69: c067 | B69: 93 | C69: 76 | D69: 0.152 | E69: 0.62 | F69: 0.618 | G69: (no heading) (26); notification of changes (7); changes to this privacy policy (5) | H69: notification_of_changes | I69: States that the company will notify users of significant changes to the use or handling of their personal information, typically via email or other prominent means. | L69: The company will notify users via email if they plan to use personal information in a manner different from the original collection purpose. | M69: The company commits to notifying users via email before making material changes to the use of their personal information. | N69: The company will notify users of substantial changes to the use of their personal information. | O69: notification_commitment (10), different_use_notification (5), notification_policy (4), commitment_notification (4), data_use_notification (3) | P69: c056 0.73, c061 0.42, c015 0.33 | Q69: merge | R69: states_how_changes_are_notified | T69: accept | V69: reviewed on the page; see decisions/page_answers_2026-10-15.json and resolutions_2026-10-15.yaml | W69: =IF(T69="accept",R69,U69)
A70: c068 | B70: 92 | C70: 73 | D70: 0.146 | E70: 0.7832 | F70: 0.665 | G70: (no heading) (19); children s privacy (13); children (6) | H70: child_data_deletion_policy | I70: States that the company will delete personal information of children under 13 if it is discovered or collected without parental consent, and may provide a process for parents to request deletion. | L70: The company will delete personal information from children under 13 if it is discovered without parental consent. | M70: The company will delete personal information from children under 13 if they learn it was collected without parental consent. | N70: The company states that it takes steps to remove personal information and terminate accounts if it becomes aware that a child under 13 has provided personal information without parental consent. | O70: data_deletion_policy (24), child_data_deletion (7), deletion_policy (5), data_removal_policy (4), deletion_of_child_data (3) | P70: c041 0.61, c019 0.59, c054 0.48 | Q70: keep | R70: deletes_children_data_if_found | T70: accept | V70: reviewed on the page; see decisions/page_answers_2026-10-15.json and resolutions_2026-10-15.yaml | W70: =IF(T70="accept",R70,U70)
A71: c069 | B71: 92 | C71: 69 | D71: 0.138 | E71: 0.7052 | F71: 0.232 | G71: (no heading) (23); personal information (8); information we collect (4) | H71: defines_personal_information | I71: States that the company defines personal information as data that can identify an individual, including various types of personally identifiable information. | L71: The company defines personal information as personally identifiable information about an individual. | M71: The company defines Personal Information as data that can identify an individual. | N71: The company defines personal information as data that can identify an individual, including contact details, demographic information, and any other information considered personal under applicable law. | O71: data_definition (26), definition_of_data (11), data_classification (7), personal_information_definition (4), definition_of_pii (4) | P71: c011 0.47, c002 0.36, c027 0.29 | Q71: keep | R71: defines_personal_information | T71: accept | V71: reviewed on the page; see decisions/page_answers_2026-10-15.json and resolutions_2026-10-15.yaml | W71: =IF(T71="accept",R71,U71)
A72: c070 | B72: 91 | C72: 75 | D72: 0.15 | E72: 0.6245 | F72: 0.381 | G72: (no heading) (10); how do we protect your information (8); security (3) | H72: no_credit_card_storage | I72: States that the company does not store credit card information on its servers or systems, with some variations on conditions or third-party involvement. | L72: The company does not store credit card information on its servers. | M72: The company does not store or save credit card numbers or information. | N72: The company does not store credit card numbers or identifying information on its servers. | O72: data_storage_policy (11), no_data_storage (4), data_use_purpose (3), third_party_use (3), data_non_storage (2) | P72: c027 0.59, c004 0.54, c043 0.51 | Q72: keep | R72: does_not_store_payment_cards | T72: accept | V72: reviewed on the page; see decisions/page_answers_2026-10-15.json and resolutions_2026-10-15.yaml | W72: =IF(T72="accept",R72,U72)
A73: c071 | B73: 91 | C73: 72 | D73: 0.144 | E73: 0.7852 | F73: 0.643 | G73: (no heading) (18); your california privacy rights (4); contacting us (3) | H73: provides_contact_information | I73: States that the company provides contact information for various purposes, including inquiries, customer service, and managing personal information, but not the specific content of the contact information. | J73: duplicate_name | L73: The company provides contact details for inquiries. | M73: The company provides contact information for inquiries. | N73: The company provides contact information for reaching a representative. | O73: contact_information (50), contact_details (18), contact_details_provision (3), contact_information_provided (2), access_to_information (2) | P73: c048 0.85, c014 0.67, c032 0.60 | Q73: merge | R73: provides_privacy_contact | T73: accept | V73: reviewed on the page; see decisions/page_answers_2026-10-15.json and resolutions_2026-10-15.yaml | W73: =IF(T73="accept",R73,U73)
A74: c072 | B74: 90 | C74: 71 | D74: 0.142 | E74: 0.6414 | F74: 0.392 | G74: (no heading) (20); how do we protect your information (5); privacy policy (3) | H74: confidentiality_requirements | I74: States that the company requires its employees, contractors, third parties, and authorized personnel to keep personal information confidential and secure. | L74: The company requires its employees to protect and keep personal information confidential. | M74: The company requires contractors to keep information secure and confidential. | N74: The company requires third-party companies to safeguard personal information according to its policies. | O74: confidentiality_requirement (9), confidentiality_commitment (9), data_confidentiality (6), confidentiality_obligations (4), confidentiality_promise (4) | P74: c007 0.59, c017 0.55, c065 0.53 | Q74: merge | R74: limits_internal_access | T74: accept | V74: reviewed on the page; see decisions/page_answers_2026-10-15.json and resolutions_2026-10-15.yaml | W74: =IF(T74="accept",R74,U74)
A75: c073 | B75: 84 | C75: 84 | D75: 0.168 | E75: 0.8577 | F75: 0.704 | G75: (no heading) (14); changes to this privacy policy (12); privacy policy changes (5) | H75: continued_use_acceptance | I75: States that continued use of the website or service after changes to the privacy policy constitutes acceptance of those changes. | L75: The company states that continued use of the Sites after changes to the Privacy Policy constitutes acceptance of the changes. | M75: Continued use of the website after changes to the privacy policy means acceptance of those changes. | N75: The company states that continued use of the service or website after changes to the privacy policy constitutes agreement to the modified terms. | O75: continued_use_acceptance (21), acceptance_of_changes (11), continued_use_agreement (11), acceptance_by_continued_use (7), user_acceptance (4) | P75: c061 0.67, c015 0.66, c056 0.56 | Q75: keep | R75: continued_use_means_acceptance | T75: accept | V75: reviewed on the page; see decisions/page_answers_2026-10-15.json and resolutions_2026-10-15.yaml | W75: =IF(T75="accept",R75,U75)

Sheet Types
A1: Type id | B1: Name | C1: Definition | D1: Positive example 1 | E1: Positive example 2 | F1: Near miss | G1: Severity weight | H1: Section hint | I1: Label source | J1: Seeds | K1: Source clusters (proposed) | L1: Claims (your decisions) | M1: Notes
A2: states_information_required_to_register | B2: states_information_required_to_register | C2: States that users must create an account or register to use the service or parts of it, and which personal information they must provide to do so (mandatory fields), as opposed to information they may choose to give. | D2: The company asks for specific personal information when users register. | E2: The company requires users to provide personal information during registration. | F2: The company collects personal information when users register or place an order on the site. | G2: 1.5 | H2: in the first half of the document | I2: First Party Collection/Use :: Collection Mode = Explicit & User Type = User with account | J2: first_party_collection_use | K2: c021 | L2: =SUMIF(Clusters!$W$2:$W$75,A2,Clusters!$B$2:$B$75) | M2: GDPR Art. 13(2)(e): whether providing the data is a requirement; definition widened after the coverage check; auto-filled, check: positive_examples, near_miss, section_hint
A3: collects_usage_data_automatically | B3: collects_usage_data_automatically | C3: States that the company automatically collects technical or usage data about visits (IP address, browser, pages viewed, log files) without the user entering it. | D3: The company collects information about the number of users visiting the website and the number of pages viewed. | E3: The company uses log files to collect various types of data for analyzing trends, administering the site, tracking user movement, and gathering demographic information. | F3: The company uses web beacons to track user visits and email opens for analytics purposes. | G3: 1.5 | H3: in the first half of the document | I3: First Party Collection/Use :: Collection Mode = Implicit & Personal Information Type = User online activities First Party Collection/Use :: Collection Mode = Implicit & Personal Information Type = IP address and device IDs First Party Collection/Use :: Collection Mode = Implicit & Personal Information Type = Computer information | J3: first_party_collection_use | K3: c001, c060 | L3: =SUMIF(Clusters!$W$2:$W$75,A3,Clusters!$B$2:$B$75) | M3: CCPA 1798.100(b): categories collected; auto-filled, check: positive_examples, near_miss, section_hint
A4: uses_cookies | B4: uses_cookies | C4: States that the company sets cookies or similar tracking technologies and what it uses them for (recognising users, remembering preferences, tracking visits). | D4: The company uses cookies to identify which pages on their website have been accessed. | E4: The company uses cookies and similar tracking technologies to access or store information. | F4: The company mentions that third-party advertising and marketing partners may use their own cookies. | G4: 1 | H4: under a heading like 'cookies', in the first half of the document | I4: First Party Collection/Use :: Personal Information Type = Cookies and tracking elements | J4: first_party_collection_use | K4: c000, c050 | L4: =SUMIF(Clusters!$W$2:$W$75,A4,Clusters!$B$2:$B$75) | M4: auto-filled, check: positive_examples, near_miss, section_hint
A5: uses_web_beacons | B5: uses_web_beacons | C5: States that the company uses web beacons, pixel tags or clear GIFs (on pages or in emails) to collect information about visits or email opens; plain cookie statements are uses_cookies. | D5: The company uses web beacons to track user visits and email opens for analytics purposes. | E5: The company uses web beacons to track which visitors interact with specific elements on web pages or emails. | F5: The company collects information about the number of users visiting the website and the number of pages viewed. | G5: 1 | H5: in the first half of the document | I5: teacher | J5: first_party_collection_use | K5: c052 | L5: =SUMIF(Clusters!$W$2:$W$75,A5,Clusters!$B$2:$B$75) | M5: auto-filled, check: positive_examples, near_miss, section_hint
A6: tracking_data_not_linked_to_identity | B6: tracking_data_not_linked_to_identity | C6: States that cookies, IP addresses or other technical data are not linked to, or not used to identify, the person (except where stated). | D6: The company does not link collected IP addresses and other information to personally identifiable information. | E6: The company does not use cookies to collect personally identifiable information. | F6: The company allows users to visit the site without providing personal information. | G6: 1 | H6: in the first half of the document | I6: teacher | J6: first_party_collection_use | K6: c027, c039 | L6: =SUMIF(Clusters!$W$2:$W$75,A6,Clusters!$B$2:$B$75) | M6: c027 was flagged mixed by the teacher (non-linking vs non-identification); both are the same promise; auto-filled, check: positive_examples, near_miss, section_hint
A7: defines_personal_information | B7: defines_personal_information | C7: Defines terms used in the policy, most often what counts as personal (personally identifiable) information or anonymous information. | D7: The company defines personal information as personally identifiable information about an individual. | E7: The company defines Personal Information as data that can identify an individual. | F7: The company discloses that the privacy policy covers the collection, use, and choices about personal information collected on or through the services. | G7: 1 | H7: near the start of the document | I7: teacher | J7: other | K7: c069 | L7: =SUMIF(Clusters!$W$2:$W$75,A7,Clusters!$B$2:$B$75) | M7: definition widened after the coverage check; auto-filled, check: positive_examples, near_miss, section_hint
A8: uses_data_to_improve_services | B8: uses_data_to_improve_services | C8: States that collected information is used to analyse, maintain or improve the website, services or user experience. | D8: The company uses collected information to improve the sites and services. | E8: The company uses collected information to improve their website and personalize your experience. | F8: The company uses data to personalize and tailor the user experience and products. | G8: 1 | H8: under a heading like 'what do we use your information for', in the first half of the document | I8: First Party Collection/Use :: Purpose = Analytics/Research | J8: first_party_collection_use | K8: c028 | L8: =SUMIF(Clusters!$W$2:$W$75,A8,Clusters!$B$2:$B$75) | M8: auto-filled, check: positive_examples, near_miss, section_hint
A9: uses_data_to_personalize | B9: uses_data_to_personalize | C9: States that collected information is used to personalise or customise content, offers or the user's experience. | D9: The company uses data to personalize and tailor the user experience and products. | E9: The company uses collected information to personalize the user experience. | F9: The company uses collected information to improve the sites and services. | G9: 1 | H9: under a heading like 'what do we use your information for', in the first half of the document | I9: First Party Collection/Use :: Purpose = Personalization/Customization | J9: first_party_collection_use | K9: c057 | L9: =SUMIF(Clusters!$W$2:$W$75,A9,Clusters!$B$2:$B$75) | M9: auto-filled, check: positive_examples, near_miss, section_hint
A10: sends_marketing_communications | B10: sends_marketing_communications | C10: States that the company uses contact details (mainly email) to send newsletters, promotions or other marketing communications about its own products and services. | D10: The company may send promotional emails about new products or special offers. | E10: The company uses information to contact users about relevant services and offers. | F10: The company collects information when users participate in contests or promotions. | G10: 1 | H10: in the first half of the document | I10: First Party Collection/Use :: Purpose = Marketing | J10: first_party_collection_use | K10: c006, c032 | L10: =SUMIF(Clusters!$W$2:$W$75,A10,Clusters!$B$2:$B$75) | M10: auto-filled, check: positive_examples, near_miss, section_hint
A11: does_not_sell_or_share | B11: does_not_sell_or_share | C11: States that the company does not sell, rent, trade or share personal information (or email addresses) with third parties, apart from any stated exceptions. | D11: The company does not sell, rent, or trade personal information to third parties. | E11: The company does not sell, trade, share, or rent the user's email address to anyone. | F11: The company does not link collected IP addresses and other information to personally identifiable information. | G11: 1.5 | H11: in the first half of the document | I11: Third Party Sharing/Collection :: Does/Does Not = Does Not | J11: third_party_sharing_collection | K11: c004, c043 | L11: =SUMIF(Clusters!$W$2:$W$75,A11,Clusters!$B$2:$B$75) | M11: CCPA 1798.115/1798.120: disclosure of sale; the negative form is the common one in this pre-2020 corpus; auto-filled, check: positive_examples, near_miss, section_hint
A12: shares_with_service_providers | B12: shares_with_service_providers | C12: States that personal information is shared with, or processed by, third-party service providers acting on the company's behalf (payment, delivery, hosting, mailing). | D12: The company may share personal information with third parties hired to perform services, under strict conditions. | E12: The company uses third party service providers to perform various functions on its behalf. | F12: The company may share personal information with business partners to fulfill requests for products or services. | G12: 1.5 | H12: in the first half of the document | I12: Third Party Sharing/Collection :: Purpose = Basic service/feature & Does/Does Not = Does Third Party Sharing/Collection :: Purpose = Service operation and security & Does/Does Not = Does | J12: third_party_sharing_collection | K12: c024, c055 | L12: =SUMIF(Clusters!$W$2:$W$75,A12,Clusters!$B$2:$B$75) | M12: GDPR Art. 13(1)(e): recipients or categories of recipients; auto-filled, check: positive_examples, near_miss, section_hint
A13: shares_with_affiliates_and_partners | B13: shares_with_affiliates_and_partners | C13: States that personal information may be shared with affiliates, subsidiaries or business partners, and for what purposes. | D13: The company may share personal information with business partners to fulfill requests for products or services. | E13: The company states that personal information may be shared with partners providing services on their behalf. | F13: The company may share personal information with third parties hired to perform services, under strict conditions. | G13: 1.5 | H13: in the first half of the document | I13: Third Party Sharing/Collection :: Third Party Entity = Other part of company/affiliate | J13: third_party_sharing_collection | K13: c030 | L13: =SUMIF(Clusters!$W$2:$W$75,A13,Clusters!$B$2:$B$75) | M13: GDPR Art. 13(1)(e): recipients; auto-filled, check: positive_examples, near_miss, section_hint
... A47: provides_privacy_contact | B47: provides_privacy_contact | C47: Tells readers how to contact the company about the policy or their information (email, address, phone, form, named contact person). | D47: The company provides a contact method for questions about the privacy policy or services. | E47: The company provides contact information for questions about privacy policy or practices. | F47: The company uses information to contact users about relevant services and offers. | G47: 1.5 | H47: in the second half of the document | I47: Other :: Other Type = Privacy contact information | J47: other | K47: c014, c048, c071 | L47: =SUMIF(Clusters!$W$2:$W$75,A47,Clusters!$B$2:$B$75) | M47: GDPR Art. 13(1)(a)-(b): contact details of the controller (and DPO). c048 and c071 had the same teacher name; auto-filled, check: positive_examples, near_miss, section_hint
A48: do_not_track_response | B48: do_not_track_response | C48: States whether and how the company responds to browser Do Not Track signals (most often that it does not). | D48: The company does not respond to browser 'Do Not Track' signals at this time. | E48: The company honors do not track signals. | F48: The company allows users to disable cookies through their web browser settings. | G48: 1 | H48: in or next to the cookies and tracking section, in the second half of the document | I48: Do Not Track | J48: do_not_track | L48: =SUMIF(Clusters!$W$2:$W$75,A48,Clusters!$B$2:$B$75) | M48: 35 claims from 29 of 500 documents, 31 of them HDBSCAN noise (too few for min cluster size 80); CalOPPA requires it for California, not GDPR/CCPA, so severity 1.0
A49: california_disclosure_rights | B49: california_disclosure_rights | C49: States the rights of California residents to learn which third parties received their information for direct marketing, and how to make the request. | D49: The company discloses that California residents can request a list of third parties to which personal information was disclosed for direct marketing purposes. | E49: California residents have the right to request a list of third parties to whom the company has disclosed personal information for direct marketing purposes. | F49: The company allows individuals to complain to a data protection authority about their collection and use of personal information. | G49: 1 | H49: near the end, under a heading like 'Your California Privacy Rights' | I49: International and Specific Audiences :: Audience Type = Californians | J49: international_specific_audiences | L49: =SUMIF(Clusters!$W$2:$W$75,A49,Clusters!$B$2:$B$75) | M49: 89 claims from 45 documents, 64 of them noise; California 'Shine the Light' (Civ. Code 1798.83), not CCPA, so severity 1.0
A50: data_collection_methods | B50: data_collection_methods | C50: States that the company collects personal information from users through various activities on the website, such as registration, placing orders, or providing information. | D50: The company collects personal information when users register or place an order on the site. | E50: The company collects various types of personal information from users, including contact details and demographic information. | F50: The company collects information about the number of users visiting the website and the number of pages viewed. | G50: 1.5 | H50: near the start of the document | I50: First Party Collection/Use :: Collection Mode = Explicit & Does/Does Not = Does | J50: first_party_collection_use | K50: c002 | L50: =SUMIF(Clusters!$W$2:$W$75,A50,Clusters!$B$2:$B$75) | M50: kept as its own item by the reviewer (group c002); severity and label source carried over from collects_information_users_provide; auto-filled, check: positive_examples, near_miss, section_hint
A51: data_use_for_services | B51: data_use_for_services | C51: States that the company uses collected personal information for providing products, services, processing orders, and customer support. | D51: The company uses collected personal information to provide products and services, process orders, and offer customer service. | E51: The company uses collected information to fulfill orders, provide quotes, process orders, notify about order status, prepare drawings, and provide information about offers or products. | F51: The company uses collected information to improve the sites and services. | G51: 1.5 | H51: in the first half of the document | I51: First Party Collection/Use :: Purpose = Basic service/feature | J51: first_party_collection_use | K51: c008 | L51: =SUMIF(Clusters!$W$2:$W$75,A51,Clusters!$B$2:$B$75) | M51: kept as its own item by the reviewer (group c008); severity and label source carried over from uses_data_to_provide_services; auto-filled, check: positive_examples, near_miss, section_hint
A52: policy_coverage | B52: policy_coverage | C52: States that the privacy policy covers the collection, use, and handling of personal information, typically specifying the scope of the policy to include the company's websites, services, and sometimes its family of companies. | D52: The company discloses that the privacy policy covers the collection, use, and choices about personal information collected on or through the services. | E52: The company explains the scope of its privacy policy to cover personal information provided through its websites. | F52: The company defines personal information as personally identifiable information about an individual. | G52: 1 | H52: near the start of the document | I52: teacher | K52: c011 | L52: =SUMIF(Clusters!$W$2:$W$75,A52,Clusters!$B$2:$B$75) | M52: kept as its own item by the reviewer (group c011); auto-filled, check: positive_examples, near_miss, section_hint
A53: user_data_control | B53: user_data_control | C53: States that users can review, update, correct or delete their personal information, how (account settings, contacting the company), and any conditions on such requests (identity verification, fees, limits). | D53: The company allows users to update and correct their personal information at any time. | E53: The company allows users to update or correct their personal information through their account or by contacting customer service. | F53: The company allows users to choose whether to provide personal information. | G53: 1.5 | H53: in the second half of the document | I53: User Access, Edit and Deletion :: Access Type = Edit information User Access, Edit and Deletion :: Access Type = View | J53: user_access_edit_deletion | K53: c012 | L53: =SUMIF(Clusters!$W$2:$W$75,A53,Clusters!$B$2:$B$75) | M53: kept as its own item by the reviewer (group c012); severity and label source carried over from access_and_correct_information; definition widened after the coverage check; auto-filled, check: positive_examples, near_miss, section_hint
A54: discloses_public_areas | B54: discloses_public_areas | C54: States that information users post in public areas (forums, reviews, profiles) can be seen and used by others and may persist or be reposted after deletion, often with a warning to be careful. | D54: The company allows users to set up public profiles that other users can view. | E54: The company discloses that information posted in public areas of the sites is publicly available and may be viewed and shared by other users. | F54: The company may share personal information with business partners to fulfill requests for products or services. | G54: 1 | H54: in the first half of the document | I54: Third Party Sharing/Collection :: Third Party Entity = Public Third Party Sharing/Collection :: Third Party Entity = Other users | J54: third_party_sharing_collection | K54: c013 | L54: =SUMIF(Clusters!$W$2:$W$75,A54,Clusters!$B$2:$B$75) | M54: kept as its own item by the reviewer (group c013); severity and label source carried over from warns_about_public_areas; definition widened after the coverage check; auto-filled, check: positive_examples, near_miss, section_hint
A55: disclose_data_rights | B55: disclose_data_rights | C55: States the user's legal rights over their personal data as rights (access, correction, objection to processing, portability, withdrawing consent, complaining to a data protection authority). | D55: The company allows individuals to complain to a data protection authority about their collection and use of personal information. | E55: The company discloses that individuals have the right to raise a complaint with the data protection regulator. | F55: The company provides a contact method for questions about the privacy policy or services. | G55: 1.5 | H55: in the second half of the document | I55: teacher | J55: user_access_edit_deletion | K55: c031 | L55: =SUMIF(Clusters!$W$2:$W$75,A55,Clusters!$B$2:$B$75) | M55: kept as its own item by the reviewer (group c031); severity and label source carried over from states_data_subject_rights; definition widened after the coverage check; auto-filled, check: positive_examples, near_miss, section_hint
A56: content_and_usage_restrictions | B56: content_and_usage_restrictions | C56: States the site's terms of use or legal conditions rather than a data practice: rules for using the site or its content, disclaimers of liability (for example use at your own risk), indemnification or release, legal penalties, or that the policy creates no contractual rights. | D56: The company states that users are not allowed to submit content that violates or infringes the rights of others. | E56: The company states that users may not modify, copy, reproduce, create derivative works, republish, display, upload, post, transmit, or distribute content without prior written consent. | F56: The Privacy Policy is governed by the laws of a specific state. | G56: 1 | H56: in the second half of the document | I56: teacher | K56: c037 | L56: =SUMIF(Clusters!$W$2:$W$75,A56,Clusters!$B$2:$B$75) | M56: kept as its own item by the reviewer (group c037); definition widened after the coverage check; auto-filled, check: positive_examples, near_miss, section_hint
A57: data_collection_contests_surveys | B57: data_collection_contests_surveys | C57: States that the company collects personal information from users through contests, surveys, and other similar activities on their website. | D57: The company collects information when users participate in contests or promotions. | E57: The company collects personal information when you participate in contests, promotions, or sweepstakes on their websites. | F57: The company may send promotional emails about new products or special offers. | G57: 1.5 | H57: in the first half of the document | I57: First Party Collection/Use :: Collection Mode = Explicit & Does/Does Not = Does | J57: first_party_collection_use | K57: c045 | L57: =SUMIF(Clusters!$W$2:$W$75,A57,Clusters!$B$2:$B$75) | M57: kept as its own item by the reviewer (group c045); severity and label source carried over from collects_information_users_provide; auto-filled, check: positive_examples, near_miss, section_hint
A58: company_identification_and_service_definition | B58: company_identification_and_service_definition | C58: Identifies who operates the site and is responsible for the information: the company or organisation and its affiliates, responsible representatives (such as a director of publication), its address, or its registration with a data-protection authority; sometimes with the services the policy covers. | D58: The company identifies itself as the owner and operator of the website or online service. | E58: The company defines the term 'Services' to include the websites, applications, and community features operated by the company. | F58: The company uses third party service providers to perform various functions on its behalf. | G58: 1.5 | H58: under a heading like 'india', in the first half of the document | I58: teacher | J58: other | K58: c047 | L58: =SUMIF(Clusters!$W$2:$W$75,A58,Clusters!$B$2:$B$75) | M58: kept as its own item by the reviewer (group c047); severity and label source carried over from identifies_operator; definition widened after the coverage check; auto-filled, check: positive_examples, near_miss, section_hint
A59: provides_third_party_links | B59: provides_third_party_links | C59: States that the company includes or provides links to third-party websites, often advising users to review the privacy policies of those sites. | D59: The company includes links to third-party sites on its website. | E59: The company provides links to other websites. | F59: The company states that third-party sites have separate and independent privacy policies. | G59: 1 | H59: in the second half of the document | I59: teacher | K59: c066 | L59: =SUMIF(Clusters!$W$2:$W$75,A59,Clusters!$B$2:$B$75) | M59: kept as its own item by the reviewer (group c066); auto-filled, check: positive_examples, near_miss, section_hint

Sheet Seeds
A1: Seed | B1: Title | C1: Proposed types | D1: Proposed exclusion | E1: Your mapping | F1: Notes
A2: first_party_collection_use | B2: First Party Collection/Use | C2: states_information_required_to_register, collects_usage_data_automatically, uses_cookies, uses_web_beacons, tracking_data_not_linked_to_identity, uses_data_to_improve_services, uses_data_to_personalize, sends_marketing_communications, data_collection_methods, data_use_for_services, data_collection_contests_surveys | E2: accept
A3: third_party_sharing_collection | B3: Third Party Sharing/Collection | C3: does_not_sell_or_share, shares_with_service_providers, shares_with_affiliates_and_partners, shares_aggregated_data, discloses_when_legally_required, transfers_data_in_business_transfer, third_party_advertising_and_cookies, disclaims_control_of_third_party_cookies, third_party_sites_and_their_policies, discloses_public_areas | E3: accept
A4: user_choice_control | B4: User Choice/Control | C4: opt_out_of_communications, opt_out_of_tracking_or_ads, browser_cookie_controls, warns_disabling_cookies_limits_site, information_provision_is_optional | E4: accept
A5: user_access_edit_deletion | B5: User Access, Edit and Deletion | C5: deletion_on_request, user_data_control, disclose_data_rights | E5: accept
A6: data_retention | B6: Data Retention | C6: states_retention_period | E6: accept
A7: data_security | B7: Data Security | C7: states_security_measures, encrypts_data_in_transit, stores_data_securely, limits_internal_access, does_not_store_payment_cards, security_not_guaranteed, advises_users_on_security | E7: accept
A8: policy_change | B8: Policy Change | C8: reserves_right_to_change_policy, states_how_changes_are_notified, continued_use_means_acceptance, states_last_updated_date | E8: accept
A9: do_not_track | B9: Do Not Track | C9: do_not_track_response | E9: accept
A10: international_specific_audiences | B10: International and Specific Audiences | C10: transfers_data_internationally, no_knowing_collection_from_children, states_minimum_age, deletes_children_data_if_found, california_disclosure_rights | E10: accept
A11: other | B11: Other | C11: defines_personal_information, states_policy_scope_and_commitment, scope_excludes_third_party_sites, consent_by_use, complies_with_laws_and_programs, governing_law_and_disputes, provides_privacy_contact, company_identification_and_service_definition | E11: accept

Sheet Claims
A1: Cluster | B1: Rank | C1: Kind | D1: Claim | E1: Document | F1: Heading
A2: c000 | B2: 1 | C2: typical | D2: The company uses cookies to identify which pages on their website have been accessed. | E2: privacy_pl:189196 | F2: What are cookies and do you use them?
A3: c000 | B3: 2 | C3: typical | D3: The company uses cookies for various purposes, including to access user information and track preferences. | E3: privacy_pl:114032 | F3: Privacy Policy
A4: c000 | B4: 3 | C4: typical | D4: The company uses cookies to uniquely identify browsers and may use both session and persistent cookies. | E4: privacy_pl:77964 | F4: Privacy Policy
A5: c000 | B5: 4 | C5: typical | D5: The company uses cookies to store preferences and data about user visits. | E5: privacy_pl:735785 | F5: USE OF COOKIES, IP ADDRESSES AND WEB BEACONS
A6: c000 | B6: 5 | C6: typical | D6: The company uses cookies to identify and track visitors and their preferences. | E6: privacy_pl:16957 | F6: Cookies
A7: c000 | B7: 6 | C7: typical | D7: The company uses cookies on the website to identify and track the user's browser. | E7: privacy_pl:148630 | F7: Information about Website Visits
A8: c000 | B8: 7 | C8: typical | D8: The company uses cookies to remember user selections and enable site functionality. | E8: opp115:928
A9: c000 | B9: 8 | C9: typical | D9: The company uses cookies to recognize users' browsers and remember preferences. | E9: privacy_pl:496936 | F9: 11. Changes to this Privacy Policy / 12. Contact us
A10: c000 | B10: 9 | C10: typical | D10: The company uses cookies to save preferences and login information and display personalized content. | E10: privacy_pl:365864 | F10: Non- Personal Information Collected By Us
A11: c000 | B11: 10 | C11: typical | D11: The company uses cookies to uniquely identify browsers to enhance and personalize the online experience. | E11: privacy_pl:931639
A12: c000 | B12: 11 | C12: random | D12: The company states that cookies are downloaded to users' computers without prompting. | E12: privacy_pl:249252 | F12: 2. How we use Cookies
A13: c000 | B13: 12 | C13: random | D13: The company uses cookies to remember user information to improve the web experience. | E13: privacy_pl:783947 | F13: Cookies
A14: c000 | B14: 13 | C14: random | D14: A cookie is a small piece of data stored on your computer's hard drive. | E14: privacy_pl:817656 | F14: What are cookies?
A15: c000 | B15: 14 | C15: random | D15: The company states that strictly necessary cookies are required for the sale of products and for the website to operate as intended. | E15: privacy_pl:665251 | F15: 2. Cookies
A16: c000 | B16: 15 | C16: random | D16: The company uses cookies to determine which set-ups are most frequently rendered. | E16: privacy_pl:927385 | F16: 7. Use of Cookies
A17: c000 | B17: 16 | C17: random | D17: The company uses cookies to understand and save user preferences for future visits. | E17: privacy_pl:735462 | F17: Do we use 'cookies'?
A18: c000 | B18: 17 | C18: random | D18: The company uses cookies to tailor content or product and service offerings. | E18: opp115:320
A19: c000 | B19: 18 | C19: random | D19: The company uses cookies to store information about visitor preferences. | E19: privacy_pl:398931 | F19: Cookies and Web Beacons
A20: c000 | B20: 19 | C20: random | D20: The company uses Google services which set cookies to store user preferences. | E20: privacy_pl:438255 | F20: Date not set
A21: c000 | B21: 20 | C21: random | D21: The company implies user consent to the use of cookies if the user continues to use the site. | E21: privacy_pl:518818 | F21: Consent for the use of cookies
A22: c001 | B22: 1 | C22: typical | D22: The company collects information about the number of users visiting the website and the number of pages viewed. | E22: privacy_pl:189196 | F22: Type of personal information we collect
A23: c001 | B23: 2 | C23: typical | D23: The company collects information about the visitor's use of the platform such as URLs visited, time spent, and actions taken. | E23: privacy_pl:912176 | F23: Information We Collect Automatically
A24: c001 | B24: 3 | C24: typical | D24: The company may use IP addresses to collect information about the frequency of visits to various parts of their sites and applications. | E24: opp115:186 | F24: IP Address
A25: c001 | B25: 4 | C25: typical | D25: The company collects information about user interactions with the website, including device and connection details. | E25: privacy_pl:799254 | F25: THE TYPE OF INFORMATION WE COLLECT FROM YOU
A26: c001 | B26: 5 | C26: typical | D26: The company collects aggregate information on what pages users access or visit. | E26: privacy_pl:584941 | F26: User's Domain Name
A27: c001 | B27: 6 | C27: typical | D27: The company collects information about computer and website usage. | E27: privacy_pl:254773
A28: c001 | B28: 7 | C28: typical | D28: The company collects data about users' computers for statistical analysis of website usage. | E28: privacy_pl:249252 | F28: 2. How we use Cookies
A29: c001 | B29: 8 | C29: typical | D29: The company automatically collects and stores information about visits, including IP address, browser type, operating system, visit date and time, accessed pages, and previous site. | E29: privacy_pl:126459 | F29: Information Automatically Collected and Stored by this Site
A30: c001 | B30: 9 | C30: typical | D30: The company collects automated information about how users use and navigate the website. | E30: privacy_pl:526683 | F30: What Information Does Red Tricycle Gather About You?
A31: c001 | B31: 10 | C31: typical | D31: The company automatically collects IP addresses and traffic information from visitors. | E31: privacy_pl:114032 | F31: Privacy Policy
A32: c001 | B32: 11 | C32: random | D32: The company uses personal information provided on the registration form for statistical purposes only. | E32: privacy_pl:202793 | F32: Is my personal information made available to others?
A33: c001 | B33: 12 | C33: random | D33: The company collects technical information from visitors. | E33: privacy_pl:590364 | F33: FAQs / What information does Poll Everywhere collect from Visitors?
A34: c001 | B34: 13 | C34: random | D34: The company collects anonymous traffic information from visitors to the site. | E34: privacy_pl:362205 | F34: WHO COLLECTS THE INFORMATION?
A35: c001 | B35: 14 | C35: random | D35: The company automatically collects information from users' browsers when they interact with the website. | E35: privacy_pl:390211
A36: c001 | B36: 15 | C36: random | D36: The company analyzes user behavior to improve services and create anonymous user profiles. | E36: privacy_pl:734271 | F36: 10. Creation of usage profiles
A37: c001 | B37: 16 | C37: random | D37: The company automatically collects information from browsers or devices when users visit the site or application. | E37: privacy_pl:674842 | F37: What we collect
A38: c001 | B38: 17 | C38: random | D38: The company collects data automatically using methods such as cookies and clear GIFs. | E38: privacy_pl:247952 | F38: Email
A39: c001 | B39: 18 | C39: random | D39: The company uses collected information to understand and monitor usage of the Site. | E39: opp115:652
A40: c001 | B40: 19 | C40: random | D40: The company uses the collected information to understand what pages and information are useful and helpful to visitors. | E40: privacy_pl:1054787 | F40: Routine Information Collection
A41: c001 | B41: 20 | C41: random | D41: The company collects information about the Internet domain and IP address from which the website is accessed. | E41: privacy_pl:809594 | F41: Other information we collect
A42: c002 | B42: 1 | C42: typical | D42: The company collects personal information when users register or place an order on the site. | E42: privacy_pl:355028 | F42: Information Collection and Use
A43: c002 | B43: 2 | C43: typical | D43: The company collects various types of personal information from users, including contact details and demographic information. | E43: privacy_pl:155718 | F43: 1. General:
A44: c002 | B44: 3 | C44: typical | D44: The company collects personal information from users when they register or provide information to a site. | E44: privacy_pl:343374 | F44: Personal Information We Collect From You
A45: c002 | B45: 4 | C45: typical | D45: The company collects personal information from users when they register or provide information to a site. | E45: privacy_pl:343370 | F45: Personal Information We Collect From You
A46: c002 | B46: 5 | C46: typical | D46: The company collects information when users place orders or enter information on the site. | E46: opp115:807
A47: c002 | B47: 6 | C47: typical | D47: The company collects information from users when they engage in various activities on the site. | E47: privacy_pl:612783 | F47: 1. What information do we collect?
A48: c002 | B48: 7 | C48: typical | D48: The company collects Personal Information from users, which includes identifiers and contact details. | E48: privacy_pl:883060 | F48: Information that We Collect
A49: c002 | B49: 8 | C49: typical | D49: The company collects personal information from users on their websites, applications, or services. | E49: privacy_pl:59678 | F49: Privacy Policy
A50: c002 | B50: 9 | C50: typical | D50: The company collects personal information from users when they engage in various activities on the sites. | E50: opp115:652 | F50: Information You Provide Directly To Us:
A51: c002 | B51: 10 | C51: typical | D51: The company collects personal information from users when they register or create an account. | E51: privacy_pl:496936 | F51: 11. Changes to this Privacy Policy / 12. Contact us
A52: c002 | B52: 11 | C52: random | D52: The company collects personal information from users on its website. | E52: privacy_pl:246162 | F52: The Information We Collect
A53: c002 | B53: 12 | C53: random | D53: The company may process demographic information including gender, date of birth, nationality, job title, and language preferences. | E53: privacy_pl:461741 | F53: We may Process the following categories of Personal Data about you:
A54: c002 | B54: 13 | C54: random | D54: The company collects contact and demographic information from users during registration. | E54: privacy_pl:802903 | F54: Privacy Policy
A55: c002 | B55: 14 | C55: random | D55: The company collects information from users at several different points on its website. | E55: privacy_pl:1054302 | F55: Information Collection and Use
A56: c002 | B56: 15 | C56: random | D56: The company collects personal data that can uniquely identify an individual. | E56: privacy_pl:544208 | F56: 2. DATOS QUE RECOPILAMOS
A57: c002 | B57: 16 | C57: random | D57: The company collects personal information directly from individuals during various interactions. | E57: privacy_pl:189196 | F57: How we collect information
A58: c002 | B58: 17 | C58: random | D58: The company collects personal information when you contact them by telephone or email. | E58: privacy_pl:891776 | F58: 1. What information do we collect?
... A76: c003 | B76: 15 | C76: random | D76: The company may disclose personal information if the user violates the Terms and Conditions. | E76: privacy_pl:684264 | F76: SECTION 4 – DISCLOSURE
A77: c003 | B77: 16 | C77: random | D77: The company may be forced to disclose information to the government or third parties under certain circumstances. | E77: privacy_pl:881052
A78: c003 | B78: 17 | C78: random | D78: The company discloses information to third parties when required by law. | E78: privacy_pl:425508 | F78: Necessary Disclosure
A79: c003 | B79: 18 | C79: random | D79: The company uses personal information for fraud detection and market research purposes. | E79: privacy_pl:58557 | F79: Use of Your Personal Information
A80: c003 | B80: 19 | C80: random | D80: The company reserves the right to access and disclose personal information to operate its systems properly. | E80: privacy_pl:872448 | F80: What information do we collect?
A81: c003 | B81: 20 | C81: random | D81: The company discloses that it may share personal data with government agencies or other third parties as authorized by applicable law. | E81: privacy_pl:721404 | F81: Free & Trial Versions of Software or Functionality
A82: c004 | B82: 1 | C82: typical | D82: The company does not sell, rent, or trade personal information to third parties. | E82: privacy_pl:239341 | F82: How We Share the Information We Collect
A83: c004 | B83: 2 | C83: typical | D83: The company does not sell, rent, or otherwise disclose personal information to third parties. | E83: privacy_pl:893785 | F83: SECTION 3 – DISCLOSURE
A84: c004 | B84: 3 | C84: typical | D84: The company does not share personal information with non-affiliated third parties without permission. | E84: privacy_pl:53451 | F84: 2. Use of Information Collected
A85: c004 | B85: 4 | C85: typical | D85: The company will not sell or share personal information with third parties. | E85: privacy_pl:774006 | F85: Collected contact information
A86: c004 | B86: 5 | C86: typical | D86: The company does not sell, rent, lease, or exchange personal information to third parties. | E86: privacy_pl:544208 | F86: 3. SHARING OF PERSONAL INFORMATION
A87: c004 | B87: 6 | C87: typical | D87: The company does not sell personal information to third parties. | E87: privacy_pl:872824 | F87: Privacy Policy
A88: c004 | B88: 7 | C88: typical | D88: The company does not sell personal information to third parties. | E88: privacy_pl:576170 | F88: Information Sharing
A89: c004 | B89: 8 | C89: typical | D89: The company does not sell personal information to third parties. | E89: privacy_pl:621224 | F89: Information Sharing
A90: c004 | B90: 9 | C90: typical | D90: The company will not share personal information with third parties without permission or legal requirement. | E90: privacy_pl:978663 | F90: Controlling your personal information
A91: c004 | B91: 10 | C91: typical | D91: The company will not sell or rent personally identifiable information to third parties, except as stated. | E91: opp115:503
A92: c004 | B92: 11 | C92: random | D92: The company will not use provided information or content for advertising or marketing purposes without prior consent from the user. | E92: privacy_pl:239750
A93: c004 | B93: 12 | C93: random | D93: The company does not share contact information with other companies for the purpose of contacting visitors. | E93: privacy_pl:767650 | F93: Surveys
A94: c004 | B94: 13 | C94: random | D94: The company does not share personal information with third parties without user consent. | E94: privacy_pl:967989 | F94: COLLECTION OF PERSONAL INFORMATION
A95: c004 | B95: 14 | C95: random | D95: The company will not disclose personally identifiable information without first receiving the user's permission, except under certain legal circumstances. | E95: privacy_pl:751999 | F95: Collecting Information
A96: c004 | B96: 15 | C96: random | D96: The company does not share personal information with third parties. | E96: privacy_pl:885480 | F96: Advertising
A97: c004 | B97: 16 | C97: random | D97: The company does not sell or share personally identifiable information to third parties without your express consent or legal requirement. | E97: privacy_pl:131098 | F97: Private Information & the Web
A98: c004 | B98: 17 | C98: random | D98: The company ensures that customer details are not sold or made available to others. | E98: privacy_pl:955136 | F98: 5. Your Credit Card Details
A99: c004 | B99: 18 | C99: random | D99: The company does not rent or sell personal information to third parties. | E99: privacy_pl:155718 | F99: 3. How Your Information is Used:
A100: c004 | B100: 19 | C100: random | D100: The company will not review, share, distribute, print, or reference customer data except as required by law or provided in the Terms of Service. | E100: privacy_pl:243848 | F100: COLLECTED INFORMATION
A101: c004 | B101: 20 | C101: random | D101: The company does not sell, trade, or rent personal information to other companies. | E101: privacy_pl:580722
A102: c005 | B102: 1 | C102: typical | D102: The company allows users to opt-out of receiving communications from the company. | E102: privacy_pl:144687 | F102: Information Sharing and Disclosure
A103: c005 | B103: 2 | C103: typical | D103: The company allows users to opt-out of receiving certain types of communications. | E103: privacy_pl:539811 | F103: 5. INFORMATION SECURITY
A104: c005 | B104: 3 | C104: typical | D104: The company provides users the opportunity to opt-out of receiving communications from the company and its partners. | E104: privacy_pl:1042150 | F104: Choice/Opt-Out
A105: c005 | B105: 4 | C105: typical | D105: The company allows users to opt-out of receiving direct mailings from the company and its partners. | E105: privacy_pl:579986 | F105: Promotion and Direct Mail
A106: c005 | B106: 5 | C106: typical | D106: The company allows users to opt-out of receiving communications. | E106: privacy_pl:824339 | F106: How to Update Your Personal Information or “Opt-out”
A107: c005 | B107: 6 | C107: typical | D107: The company provides users with the opportunity to opt-out of receiving future communications from the company and its partners at any time. | E107: privacy_pl:928502 | F107: Choice/Opt-Out
A108: c005 | B108: 7 | C108: typical | D108: The company provides users the opportunity to opt-out of receiving communications from the company and its partners. | E108: privacy_pl:1042145 | F108: Choice/Opt-Out
A109: c005 | B109: 8 | C109: typical | D109: The company grants users the opportunity to opt out of further communication upon registration. | E109: opp115:1673
A110: c005 | B110: 9 | C110: typical | D110: The company allows users to opt out of receiving email newsletters by selecting specific links or following opt-out instructions. | E110: privacy_pl:856042 | F110: 10. Your Choices and Selecting Your Privacy Preferences
A111: c005 | B111: 10 | C111: typical | D111: The company allows users to opt out of receiving unsolicited communications at the time of signing up. | E111: privacy_pl:603038 | F111: 8. Can you opt out of receiving unsolicited communications from Online Agency?
A112: c005 | B112: 11 | C112: random | D112: The company allows users to opt out of disclosures to third parties for marketing purposes. | E112: privacy_pl:247952 | F112: Our Disclosure of Your Information
A113: c005 | B113: 12 | C113: random | D113: The company provides an opt-out mechanism for commercial emails. | E113: privacy_pl:799450 | F113: ACCESS/CHOICE/RETENTION
A114: c005 | B114: 13 | C114: random | D114: The company allows users to opt-out of receiving communications from the company and its partners. | E114: privacy_pl:1012279
A115: c005 | B115: 14 | C115: random | D115: The company allows users to opt-out of receiving future offers or promotional materials. | E115: privacy_pl:566538 | F115: 4. How can I stop receiving notices about future offers or to stop my Personal Information from being shared with third parties?
A116: c005 | B116: 15 | C116: random | D116: The company allows users to opt out of any or all contacts at any time. | E116: opp115:1673
A117: c005 | B117: 16 | C117: random | D117: The company provides a method to opt-out of having name and postal address information shared for marketing purposes. | E117: privacy_pl:145691 | F117: Disclosures of Name and Postal Address Information.
...

Sheet Noise sample
A1: Claim | B1: Document | C1: Heading | D1: Nearest cluster | E1: Similarity
A2: The company collects non-personally-identifiable information about users served ads by the company and its advertising agents. | B2: privacy_pl:496836 | C2: Information SpaceWar Collects | D2: c044 | E2: 0.468
A3: The company uses IP addresses to analyse trends, administer the site, track user movement, and gather demographic information, but does not link IP addresses to personally identifiable information. | B3: privacy_pl:961999 | C3: PRIVACY POLICY | D3: c001 | E3: 0.574
A4: The company collects and stores information, including the friend's email address, to send an invitation and track the referral program. | B4: privacy_pl:533526 | C4: Friend Referrals | D4: c002 | E4: 0.499
A5: The company may disclose personally identifiable information to third parties for marketing purposes. | B5: opp115:320 | D5: c024 | E5: 0.627
A6: The company discloses that California residents can request a list of third parties to which their personal information was disclosed for marketing purposes. | B6: privacy_pl:319842 | C6: NOTICE TO CALIFORNIA RESIDENTS/YOUR CALIFORNIA PRIVACY RIGHTS | D6: c024 | E6: 0.444
A7: Information from transactions is maintained in third-party databases for accounting and billing purposes. | B7: privacy_pl:631919 | C7: Product Purchases | D7: c055 | E7: 0.458
A8: The company researches demographics and interests based on registration information, server log files, or surveys. | B8: privacy_pl:603038 | C8: 2. How does Online Agency use your information? | D8: c001 | E8: 0.61
A9: The company provides a contact method for users to exercise their rights under data protection laws. | B9: privacy_pl:518818 | C9: YOUR RIGHTS / Your European Privacy Rights | D9: c031 | E9: 0.615
A10: The company reports aggregate information to advertisers and uses click-stream data for internal purposes. | B10: privacy_pl:991957 | C10: Automatic collection when you access our Services | D10: c049 | E10: 0.493
A11: The company may use the friend's information to provide information about the company and related products and services. | B11: privacy_pl:373260 | C11: Tell-A-Friend | D11: c030 | E11: 0.444
A12: The company grants users the ability to disable the sharing feature in their account settings. | B12: privacy_pl:590364 | C12: Who can see my polls? | D12: c054 | E12: 0.629
A13: The company may process personal data based on legitimate interests, where the company has a legitimate interest in carrying out the processing for business purposes, and that interest is not overridden by the individual's rights. | B13: privacy_pl:461741 | C13: E. Lawful basis for Processing Personal Data | D13: c008 | E13: 0.234
A14: The company discloses personal information to debt collection agencies to recover amounts owed. | B14: privacy_pl:731825 | C14: Dealing with Personal Information | D14: c006 | E14: 0.302
A15: The company may charge a fee to cover costs incurred in providing a copy of personal information. | B15: privacy_pl:248478 | C15: 7. Your rights | D15: c021 | E15: 0.219
A16: The company provides a physical address for inquiries about the Privacy Policy. | B16: privacy_pl:62353 | C16: Questions | D16: c048 | E16: 0.642
A17: The company allows individuals to provide information for job applications or enquiries. | B17: privacy_pl:142469 | C17: Job Applications | D17: c021 | E17: 0.393
... A42: The company uses the collected information for website administration, trend analysis, and usage. | B42: privacy_pl:217721 | C42: Log Files and Cookies | D42: c008 | E42: 0.623
A43: The company uses both personal and aggregated information for various purposes. | B43: privacy_pl:68861 | D43: c069 | E43: 0.436
A44: The company will respond to requests to delete or change personal information within 30 days. | B44: privacy_pl:59106 | D44: c026 | E44: 0.527
A45: The company shares your name and shipping address with distribution and shipping partners when shipping physical goods to you. | B45: privacy_pl:562491 | C45: 3: HOW WE USE INFORMATION / To Provide You With Quarterly Services | D45: c030 | E45: 0.446
A46: The company uses third-party advertisements that may use cookies and web beacons. | B46: privacy_pl:648024 | C46: Cookies | D46: c053 | E46: 0.851
A47: The company directs Marketing Affiliates to use and protect information in a manner consistent with the Privacy Policy. | B47: privacy_pl:319842 | C47: WHEN DO WE SHARE YOUR PERSONAL INFORMATION? | D47: c010 | E47: 0.359
A48: If the user does not enable the location-based service, the app will not transmit location information to the company. | B48: opp115:652 | C48: Location Information | D48: c034 | E48: 0.317
A49: The company receives personal information from employers when users have received leased vehicles in the context of their employment. | B49: privacy_pl:686001 | C49: How do we receive and process your information? | D49: c002 | E49: 0.436
A50: The company maintains records of policy coverages, premiums, and payment history. | B50: opp115:1106 | C50: What Personal Information Do We Have and Where Do We Get It | D50: c060 | E50: 0.308
A51: The company requires contact and financial information for order processing. | B51: privacy_pl:1045510 | C51: Information Collection | D51: c008 | E51: 0.548
A52: The company does not sell, trade, or transfer personally identifiable information to outside parties. | B52: privacy_pl:911020 | C52: Do we disclose any information to outside parties? | D52: c004 | E52: 0.714
A53: The company partners with a third party to display advertising on their website or manage their advertising on other sites, using technologies such as cookies to gather information about users' activities. | B53: privacy_pl:518540 | C53: Cookie and Tracking Technologies | D53: c053 | E53: 0.713
A54: The company may pass your contact details to third parties for marketing purposes if your relationship is governed by standard business terms and conditions. | B54: privacy_pl:891776 | C54: 3. Use of your information | D54: c044 | E54: 0.504
A55: Third-party sign-in services allow users to share information about their activities on the company's services with their network. | B55: privacy_pl:991957 | C55: Single Sign-On | D55: c024 | E55: 0.487
A56: The company states that third-party ad networks use various technologies to measure ad effectiveness and personalize content. | B56: privacy_pl:862588 | C56: DoubleClick DART Cookie | D56: c058 | E56: 0.419
... A71: The company collects aggregated (non-personally identifiable) information through tracking on the website. | B71: privacy_pl:144687 | C71: Collection | D71: c001 | E71: 0.646
A72: The company provides a contact method for concerns about information from or about anyone under 13. | B72: privacy_pl:672202 | D72: c019 | E72: 0.53
A73: The company uses IP addresses to analyze trends, administer the site, track user movement, and gather demographic information, but IP addresses are not linked to personal information. | B73: privacy_pl:566538 | C73: 1. What information does the Company collect about me on this Site? | D73: c001 | E73: 0.606
A74: The company collects demographic and profile data for various purposes. | B74: privacy_pl:1042150 | D74: c002 | E74: 0.56
A75: The company specifies eligibility criteria for the promotion. | B75: privacy_pl:1018282 | C75: OFFICIAL RULES | D75: c045 | E75: 0.319
A76: The company states that third-party cookies are independent and subject to their own privacy policies. | B76: privacy_pl:405423 | C76: Trapcall.com Cookies | D76: c023 | E76: 0.64
A77: The company uses personal information to respond to inquiries, process orders, and provide account information. | B77: privacy_pl:626412 | C77: FOR OUR CONSUMERS | D77: c008 | E77: 0.525
A78: The company will notify individuals if their personal information is compromised due to a security breach. | B78: privacy_pl:605963 | C78: 7. Compromise of Personal Information | D78: c067 | E78: 0.507
A79: The technological tools send participating advertisers information such as the user's IP address, ISP, browser, and Flash software information. | B79: privacy_pl:1058891 | C79: Advertisment | D79: c042 | E79: 0.447
A80: Material changes to the Privacy Policy will take effect after a specified period. | B80: privacy_pl:368571 | C80: Amendments to this Privacy Policy | D80: c061 | E80: 0.741
A81: The company collects information to provide and improve its site, application, services, features, and content. | B81: privacy_pl:688251 | C81: DATA COLLECTED | D81: c028 | E81: 0.742
A82: The company discloses personally identifiable information to third parties if the individual gives permission. | B82: privacy_pl:362205 | C82: WITH WHOM WILL YOUR INFORMATION BE SHARED? | D82: c024 | E82: 0.537
A83: The company includes or offers third party products or services on the website at its discretion. | B83: privacy_pl:890874 | C83: Do we disclose any information to outside parties? | D83: c058 | E83: 0.598
A84: The company will inform the person requesting the licence of any expected delays in the delivery of the software. | B84: privacy_pl:126095 | C84: Delivery Policy | D84: c067 | E84: 0.328
A85: The company allows users to withdraw consent for contact, collection, use, or disclosure of their information at any time. | B85: privacy_pl:684264 | C85: SECTION 3 – CONSENT | D85: c059 | E85: 0.55
A86: Third-party advertising companies may use cookies and clear GIFs to measure advertising effectiveness. | B86: privacy_pl:425508 | C86: Online Ad Serving | D86: c053 | E86: 0.772
... A92: The company collects personal information only if you provide it through specific forms. | B92: privacy_pl:361201 | C92: WEBSITE INFORMATION: | D92: c002 | E92: 0.51
A93: The company does not charge for its service but users are responsible for their carrier's standard text messaging rates. | B93: privacy_pl:565220 | D93: c047 | E93: 0.234
A94: The company logs certain information, such as IP address and hostname, for statistical and security reasons. | B94: privacy_pl:1045471 | C94: Privacy Policy | D94: c060 | E94: 0.641
A95: Third-party ad networks may use additional technologies to measure advertisement effectiveness and personalize content. | B95: privacy_pl:742029 | C95: Amazon | D95: c050 | E95: 0.462
A96: The collected information is used for targeting ads and measuring ad effectiveness. | B96: privacy_pl:496836 | C96: Consumer Information | D96: c049 | E96: 0.502
A97: Third-party ad networks use various technologies to measure ad effectiveness and personalize content. | B97: privacy_pl:398931 | C97: DoubleClick DART Cookie | D97: c058 | E97: 0.458
A98: The website uses three types of electronic access, storage, and/or tracing devices. | B98: privacy_pl:725191 | C98: 2. Cookies | D98: c065 | E98: 0.356
A99: The company will post a prominent notice on their website if they make material changes to their privacy practices that do not affect already stored user information. | B99: privacy_pl:292234 | D99: c061 | E99: 0.705
A100: The company collects anonymous information from standard usage logs. | B100: privacy_pl:362205 | C100: WHAT INFORMATION IS, OR MAY BE, COLLECTED FROM YOU? | D100: c060 | E100: 0.622
A101: The company collects information from third parties as part of marketing efforts. | B101: privacy_pl:19411 | C101: COLLECTION AND USE OF PERSONAL AND NON-PERSONAL INFORMATION | D101: c058 | E101: 0.573
